[{"email":"eugénia_95@example.com","password":"Pauko95(","name":"Eugénia Pauko"},
{"email":"Κυπάρισσος_85@example.com","password":"Λύκος85}}","name":"Κυπάρισσος Λύκος"},
{"email":"Валери-97@example.com","password":"ТОДОРОВА97\u0026","name":"Валери ТОДОРОВА"},
{"email":"caterina-87@example.com","password":"Râpeanu87@*","name":"Caterina Râpeanu"},
{"email":"fernando_96@example.com","password":"Uribe96~$","name":"Fernando Uribe"},
{"email":"norica87@example.com","password":"Florea87!)","name":"Norica Florea"},
{"email":"anatolie91@example.com","password":"Buia91+","name":"Anatolie Buia"},
{"email":"marieconrad@example.com","password":"Conrad88^#","name":"Marie Conrad"},
{"email":"tincuța_93@example.com","password":"Bocoianu93{)","name":"Tincuța Bocoianu"},
{"email":"Кристина90@example.com","password":"Щёголевa90)*","name":"Кристина Щёголевa"},
{"email":"marin_92@example.com","password":"Miculescu92!$","name":"Marin Miculescu"},
{"email":"danielle-90@example.com","password":"Ryan90(@","name":"Danielle Ryan"},
{"email":"georgia-91@example.com","password":"Brown91_","name":"Georgia Brown"},
{"email":"reyna-93@example.com","password":"Arreola93=}","name":"Reyna Arreola"},
{"email":"abbie.king@example.com","password":"King95}^","name":"Abbie King"},
{"email":"casiana-92@example.com","password":"Proca92\u0026!","name":"Casiana Proca"},
{"email":"مروة97@example.com","password":"الربيش97$!","name":"مروة الربيش"},
{"email":"nicodim90@example.com","password":"Chișu90%^","name":"Nicodim Chișu"},
{"email":"syrine88@example.com","password":"Langlois88%^","name":"Syrine Langlois"},
{"email":"Ισίδωρος90@example.com","password":"Αλεβίζος90*$","name":"Ισίδωρος Αλεβίζος"},
{"email":"Λουκάς_85@example.com","password":"Αλεξανδρίδης85%!","name":"Λουκάς Αλεξανδρίδης"},
{"email":"Θεοφάνης97@example.com","password":"Λόντος97^\u0026","name":"Θεοφάνης Λόντος"},
{"email":"龚-榕@example.com","password":"榕94~+","name":"龚 榕"},
{"email":"petronela96@example.com","password":"Dejeu96*$","name":"Petronela Dejeu"},
{"email":"bibiána_98@example.com","password":"Pika98{$","name":"Bibiána Pika"},
{"email":"kevinwarren@example.com","password":"Warren86}%","name":"Kevin Warren"},
{"email":"corinaeiade@example.com","password":"Eiade90!^","name":"Corina Eiade"},
{"email":"wiktoria-87@example.com","password":"Baran87=)","name":"Wiktoria Baran"},
{"email":"baranyi_86@example.com","password":"Ottó86#$","name":"Baranyi Ottó"},
{"email":"Κλυτίος_84@example.com","password":"Νικολαΐδης84%+","name":"Κλυτίος Νικολαΐδης"},
{"email":"tudorlascu@example.com","password":"Lascu86*#","name":"Tudor Lascu"},
{"email":"钱.薰@example.com","password":"薰91*)","name":"钱 薰"},
{"email":"luizavîlcu@example.com","password":"Vîlcu87_}","name":"Luiza Vîlcu"},
{"email":"Ελίνα-91@example.com","password":"Αθανασίου91%(","name":"Ελίνα Αθανασίου"},
{"email":"felipe-94@example.com","password":"Londoño94\u0026@","name":"Felipe Londoño"},
{"email":"constantina de la_95@example.com","password":"Marina95(~","name":"Constantina De la Marina"},
{"email":"blanduzia96@example.com","password":"Aman96*=","name":"Blanduzia Aman"},
{"email":"Μίμας-86@example.com","password":"Ιωάννου86)","name":"Μίμας Ιωάννου"},
{"email":"george84@example.com","password":"Nemescu84@+","name":"George Nemescu"},
{"email":"sabina97@example.com","password":"Baconschi97%%","name":"Sabina Baconschi"},
{"email":"františka-86@example.com","password":"Hus86_\u0026","name":"Františka Hus"},
{"email":"cornelia_89@example.com","password":"Boștină89)*","name":"Cornelia Boștină"},
{"email":"sabina-96@example.com","password":"Andrieș96@#","name":"Sabina Andrieș"},
{"email":"codin88@example.com","password":"Tapalagă88@#","name":"Codin Tapalagă"},
{"email":"arthur-85@example.com","password":"Romero85^*","name":"Arthur Romero"},
{"email":"brian-91@example.com","password":"Mitchell91$!","name":"Brian Mitchell"},
{"email":"sara-watson@example.com","password":"Watson97(}","name":"Sara Watson"},
{"email":"lucian_88@example.com","password":"Hrușcă88(%","name":"Lucian Hrușcă"},
{"email":"lucashill@example.com","password":"Hill94{)","name":"Lucas Hill"},
{"email":"郝_漩@example.com","password":"漩87_*","name":"郝 漩"},
{"email":"الجوري85@example.com","password":"السنيدي85!+","name":"الجوري السنيدي"},
{"email":"chikodi95@example.com","password":"Dan-Asebe95){","name":"Chikodi Dan-Asebe"},
{"email":"meera97@example.com","password":"Awasthi97=^","name":"Meera Awasthi"},
{"email":"serena.rossi@example.com","password":"Rossi87{","name":"Serena Rossi"},
{"email":"dorina_96@example.com","password":"Ciocârlan96^!","name":"Dorina Ciocârlan"},
{"email":"emily_85@example.com","password":"Mitchell85(","name":"Emily Mitchell"},
{"email":"lola-blanc@example.com","password":"Blanc93%~","name":"Lola Blanc"},
{"email":"medard.rak@example.com","password":"Rak85\u0026$","name":"Medard Rak"},
{"email":"geir.sæther@example.com","password":"Sæther97+~","name":"Geir Sæther"},
{"email":"冯_娇@example.com","password":"娇89={","name":"冯 娇"},
{"email":"eusebia95@example.com","password":"Cosmovici95%","name":"Eusebia Cosmovici"},
{"email":"iris.Șerb@example.com","password":"Șerb86#!","name":"Iris Șerb"},
{"email":"jana-bodescu@example.com","password":"Bodescu88%^","name":"Jana Bodescu"},
{"email":"lưubảo@example.com","password":"Bảo94~#","name":"Lưu Bảo"},
{"email":"Κλεομένης93@example.com","password":"Καραμήτσος93_^","name":"Κλεομένης Καραμήτσος"},
{"email":"Ηριδανός96@example.com","password":"Ελευθερόπουλος96)^","name":"Ηριδανός Ελευθερόπουλος"},
{"email":"옥.미경@example.com","password":"미경88!","name":"옥 미경"},
{"email":"silvana_93@example.com","password":"Almășan93}\u0026","name":"Silvana Almășan"},
{"email":"dylandavis@example.com","password":"Davis94_$","name":"Dylan Davis"},
{"email":"nesrin.vural@example.com","password":"Vural93$(","name":"Nesrin Vural"},
{"email":"flora_97@example.com","password":"Țenescu97}*","name":"Flora Țenescu"},
{"email":"عرشیا96@example.com","password":"نوبختی96^^","name":"عرشیا نوبختی"},
{"email":"csordás_92@example.com","password":"Jázmin92}\u0026","name":"Csordás Jázmin"},
{"email":"דינה95@example.com","password":"יאיר95((","name":"דינה יאיר"},
{"email":"shyam_97@example.com","password":"Aangdembe97#$","name":"Shyam Aangdembe"},
{"email":"teodora_87@example.com","password":"Preoteasa87\u0026~","name":"Teodora Preoteasa"},
{"email":"Μέροπας-93@example.com","password":"Αλεξάνδρου93_","name":"Μέροπας Αλεξάνδρου"},
{"email":"samina_dar@example.com","password":"Dar95\u0026~","name":"Samina Dar"},
{"email":"eduardo-91@example.com","password":"Durán91+_","name":"Eduardo Durán"},
{"email":"ilgın.tunç@example.com","password":"Tunç97*#","name":"Ilgın Tunç"},
{"email":"david_92@example.com","password":"Quezada92+(","name":"David Quezada"},
{"email":"heracleea_85@example.com","password":"Braghiș85@\u0026","name":"Heracleea Braghiș"},
{"email":"bacsó-97@example.com","password":"Ferenc97#^","name":"Bacsó Ferenc"},
{"email":"chirag_93@example.com","password":"Dasgupta93$(","name":"Chirag Dasgupta"},
{"email":"giuseppe_91@example.com","password":"Conte91#\u0026","name":"Giuseppe Conte"},
{"email":"laura89@example.com","password":"Lăzăreanu89\u0026*","name":"Laura Lăzăreanu"},
{"email":"Μέροπας-88@example.com","password":"Γερμανός88$=","name":"Μέροπας Γερμανός"},
{"email":"daniel97@example.com","password":"Kristensen97@%","name":"Daniel Kristensen"},
{"email":"emma-lloyd@example.com","password":"Lloyd88)=","name":"Emma Lloyd"},
{"email":"victor-90@example.com","password":"Chelcea90%\u0026","name":"Victor Chelcea"},
{"email":"antoniu_94@example.com","password":"Pascali94$","name":"Antoniu Pascali"},
{"email":"luminița-98@example.com","password":"Sassu98%","name":"Luminița Sassu"},
{"email":"zenovia_86@example.com","password":"Cocea86!#","name":"Zenovia Cocea"},
{"email":"romane_92@example.com","password":"Leclercq92%~","name":"Romane Leclercq"},
{"email":"teohari-aman@example.com","password":"Aman96%%","name":"Teohari Aman"},
{"email":"binod_tashi@example.com","password":"Tashi94_!","name":"Binod Tashi"},
{"email":"anghel94@example.com","password":"Iordache94^(","name":"Anghel Iordache"},
{"email":"sergiu90@example.com","password":"Poenaru90(@","name":"Sergiu Poenaru"},
{"email":"heather89@example.com","password":"Bowman89$","name":"Heather Bowman"},
{"email":"中川恵@example.com","password":"恵94#{","name":"中川 恵"},
{"email":"Ágatha-90@example.com","password":"Rodrigues90^#","name":"Ágatha Rodrigues"},
{"email":"ben-moore@example.com","password":"Moore94%_","name":"Ben Moore"},
{"email":"georgian98@example.com","password":"Bunea98=#","name":"Georgian Bunea"},
{"email":"felipe-87@example.com","password":"Jímenez87_=","name":"Felipe Jímenez"},
{"email":"anatolie_90@example.com","password":"Braghiș90+{","name":"Anatolie Braghiș"},
{"email":"bekzhan-86@example.com","password":"Rysbekov86{","name":"Bekzhan Rysbekov"},
{"email":"Ερατοσθένης_88@example.com","password":"Λιάπης88{","name":"Ερατοσθένης Λιάπης"},
{"email":"jason_owens@example.com","password":"Owens92+^","name":"Jason Owens"},
{"email":"mariana98@example.com","password":"Figueiredo98_~","name":"Mariana Figueiredo"},
{"email":"salamon-90@example.com","password":"Kálmán90(*","name":"Salamon Kálmán"},
{"email":"maja.strand@example.com","password":"Strand93~{","name":"Maja Strand"},
{"email":"tanjakotnik@example.com","password":"Kotnik88~(","name":"Tanja Kotnik"},
{"email":"blažena-87@example.com","password":"Janka87%)","name":"Blažena Janka"},
{"email":"tom-tom@example.com","password":"Tom84!~","name":"Tom Tom"},
{"email":"lidia-93@example.com","password":"Guillén93$_","name":"Lidia Guillén"},
{"email":"gregorian_93@example.com","password":"Mureșan93%@","name":"Gregorian Mureșan"},
{"email":"viktor-91@example.com","password":"Štefan91@$","name":"Viktor Štefan"},
{"email":"laracorreia@example.com","password":"Correia90#)","name":"Lara Correia"},
{"email":"yamkala_raut@example.com","password":"Raut98(_","name":"Yamkala Raut"},
{"email":"nadeem_rana@example.com","password":"Rana86}^","name":"Nadeem Rana"},
{"email":"kylychbek_89@example.com","password":"Shadiyarbekov89=^","name":"Kylychbek Shadiyarbekov"},
{"email":"zámbó_97@example.com","password":"Izabella97#~","name":"Zámbó Izabella"},
{"email":"amparo90@example.com","password":"Romero90%}","name":"Amparo Romero"},
{"email":"amechie_93@example.com","password":"Adamu93)!","name":"Amechie Adamu"},
{"email":"Διονύσιος-90@example.com","password":"Παπανικολάου90*=","name":"Διονύσιος Παπανικολάου"},
{"email":"sandhya85@example.com","password":"Regmi85%(","name":"Sandhya Regmi"},
{"email":"virginia98@example.com","password":"Caramitru98!#","name":"Virginia Caramitru"},
{"email":"dacian90@example.com","password":"Argetoianu90~@","name":"Dacian Argetoianu"},
{"email":"mohamed-92@example.com","password":"Rousseau92*","name":"Mohamed Rousseau"},
{"email":"Ștefana-89@example.com","password":"Herescu89#}","name":"Ștefana Herescu"},
{"email":"panait-97@example.com","password":"Bădulescu97{}","name":"Panait Bădulescu"},
{"email":"cristian95@example.com","password":"Almașanu95^*","name":"Cristian Almașanu"},
{"email":"abylaykhan90@example.com","password":"Kumushbekov90}!","name":"Abylaykhan Kumushbekov"},
{"email":"himal96@example.com","password":"Manandhar96$+","name":"Himal Manandhar"},
{"email":"zenovia86@example.com","password":"Udilă86\u0026!","name":"Zenovia Udilă"},
{"email":"oleg_korec@example.com","password":"Korec89%=","name":"Oleg Korec"},
{"email":"fiona94@example.com","password":"Vatamanu94){","name":"Fiona Vatamanu"},
{"email":"madarász95@example.com","password":"Bendegúz95}_","name":"Madarász Bendegúz"},
{"email":"Λουΐζα_95@example.com","password":"Λούλης95)_","name":"Λουΐζα Λούλης"},
{"email":"zhotay84@example.com","password":"Bayelov84$(","name":"Zhotay Bayelov"},
{"email":"vanessa87@example.com","password":"Schmidt87)#","name":"Vanessa Schmidt"},
{"email":"Αφαρέας_95@example.com","password":"Δασκαλοπούλου95^}","name":"Αφαρέας Δασκαλοπούλου"},
{"email":"marta-94@example.com","password":"Medeleanu94*","name":"Marta Medeleanu"},
{"email":"elvira.huidu@example.com","password":"Huidu86=$","name":"Elvira Huidu"},
{"email":"顾_姑@example.com","password":"姑95{^","name":"顾 姑"},
{"email":"francisca-94@example.com","password":"Gil94=#","name":"Francisca Gil"},
{"email":"Αρτέμης-91@example.com","password":"Ελευθεριάδης91}}","name":"Αρτέμης Ελευθεριάδης"},
{"email":"rodrigo-96@example.com","password":"Arias96)(","name":"Rodrigo Arias"},
{"email":"rita_91@example.com","password":"Upadhyaya91^!","name":"Rita Upadhyaya"},
{"email":"paul.chișu@example.com","password":"Chișu87)*","name":"Paul Chișu"},
{"email":"sara_smits@example.com","password":"Smits84~@","name":"Sara Smits"},
{"email":"bogdana90@example.com","password":"Josan90!\u0026","name":"Bogdana Josan"},
{"email":"nisan-talan@example.com","password":"Talan94+$","name":"Nisan Talan"},
{"email":"luminița-89@example.com","password":"Păunescu89*+","name":"Luminița Păunescu"},
{"email":"cedrin_96@example.com","password":"Țenescu96!","name":"Cedrin Țenescu"},
{"email":"paulandrews@example.com","password":"Andrews84\u0026~","name":"Paul Andrews"},
{"email":"daniel91@example.com","password":"Almaș91!{","name":"Daniel Almaș"},
{"email":"esteban-92@example.com","password":"Delgado92~=","name":"Esteban Delgado"},
{"email":"madison_91@example.com","password":"Morton91%@","name":"Madison Morton"},
{"email":"leif.holm@example.com","password":"Holm85){","name":"Leif Holm"},
{"email":"bobby_white@example.com","password":"White84~~","name":"Bobby White"},
{"email":"باران_89@example.com","password":"منصوری89}","name":"باران منصوری"},
{"email":"summer94@example.com","password":"Walker94_%","name":"Summer Walker"},
{"email":"alessio84@example.com","password":"Conte84_#","name":"Alessio Conte"},
{"email":"blake_page@example.com","password":"Page93~_","name":"Blake Page"},
{"email":"Λέων_84@example.com","password":"Καραμήτσος84(!","name":"Λέων Καραμήτσος"},
{"email":"mesut90@example.com","password":"Sevindi90$@","name":"Mesut Sevindi"},
{"email":"relu95@example.com","password":"Esinencu95%@","name":"Relu Esinencu"},
{"email":"kushum-93@example.com","password":"Ranabhat93\u0026{","name":"Kushum Ranabhat"},
{"email":"cecilia-98@example.com","password":"Țuțea98{!","name":"Cecilia Țuțea"},
{"email":"tibor_93@example.com","password":"Michálek93}(","name":"Tibor Michálek"},
{"email":"nick_84@example.com","password":"Dietrich84%=","name":"Nick Dietrich"},
{"email":"alessandro89@example.com","password":"Lombardi89##","name":"Alessandro Lombardi"},
{"email":"hugo-masný@example.com","password":"Masný90(~","name":"Hugo Masný"},
{"email":"david_90@example.com","password":"Christie90#_","name":"David Christie"},
{"email":"branislav96@example.com","password":"Riška96+*","name":"Branislav Riška"},
{"email":"brooke_hill@example.com","password":"Hill84+~","name":"Brooke Hill"},
{"email":"dinuvianu@example.com","password":"Vianu94$@","name":"Dinu Vianu"},
{"email":"Δημόδοκος89@example.com","password":"Παπαδάκης89#*","name":"Δημόδοκος Παπαδάκης"},
{"email":"Λαοδάμας93@example.com","password":"Αντωνοπούλου93+","name":"Λαοδάμας Αντωνοπούλου"},
{"email":"petronela_91@example.com","password":"Rosetti91%*","name":"Petronela Rosetti"},
{"email":"Αυτόλυκος_84@example.com","password":"Λιακόπουλος84@","name":"Αυτόλυκος Λιακόπουλος"},
{"email":"hatvani_92@example.com","password":"Sámuel92\u0026$","name":"Hatvani Sámuel"},
{"email":"igor-kližan@example.com","password":"Kližan85@^","name":"Igor Kližan"},
{"email":"felicia-94@example.com","password":"Petruș94#$","name":"Felicia Petruș"},
{"email":"david-94@example.com","password":"McDermott94!~","name":"David McDermott"},
{"email":"sonia.dogaru@example.com","password":"Dogaru95!{","name":"Sonia Dogaru"},
{"email":"tudor_97@example.com","password":"Botescu97!{","name":"Tudor Botescu"},
{"email":"Δάρδανος-84@example.com","password":"Μεσσηνέζης84@=","name":"Δάρδανος Μεσσηνέζης"},
{"email":"nehir_İlhan@example.com","password":"İlhan96)","name":"Nehir İlhan"},
{"email":"peter86@example.com","password":"Willemsen86\u0026%","name":"Peter Willemsen"},
{"email":"juan_reid@example.com","password":"Reid88(\u0026","name":"Juan Reid"},
{"email":"pap.fruzsina@example.com","password":"Fruzsina84+@","name":"Pap Fruzsina"},
{"email":"gabi-97@example.com","password":"Fiscuteanu97}!","name":"Gabi Fiscuteanu"},
{"email":"arturo88@example.com","password":"Zamora88()","name":"Arturo Zamora"},
{"email":"luciefaure@example.com","password":"Faure85+^","name":"Lucie Faure"},
{"email":"Ασπάσιος-91@example.com","password":"Ζωγράφος91}+","name":"Ασπάσιος Ζωγράφος"},
{"email":"marine-lamy@example.com","password":"Lamy95%","name":"Marine Lamy"},
{"email":"rosa-85@example.com","password":"Kairatov85+)","name":"Rosa Kairatov"},
{"email":"corentin-86@example.com","password":"Dumas86_}","name":"Corentin Dumas"},
{"email":"Εύηνος_83@example.com","password":"Λαμπρόπουλος83@)","name":"Εύηνος Λαμπρόπουλος"},
{"email":"aurora96@example.com","password":"Bocoianu96}@","name":"Aurora Bocoianu"},
{"email":"frederic94@example.com","password":"Grecescu94#^","name":"Frederic Grecescu"},
{"email":"pieter-91@example.com","password":"Huisman91+{","name":"Pieter Huisman"},
{"email":"sabina-87@example.com","password":"Donici87_}","name":"Sabina Donici"},
{"email":"joan.navarro@example.com","password":"Navarro95!(","name":"Joan Navarro"},
{"email":"cristobal-88@example.com","password":"Tatomirescu88!%","name":"Cristobal Tatomirescu"},
{"email":"anabela-88@example.com","password":"Datcu88({","name":"Anabela Datcu"},
{"email":"nadia-98@example.com","password":"Croitor98(","name":"Nadia Croitor"},
{"email":"daniel-92@example.com","password":"Montoya92!)","name":"Daniel Montoya"},
{"email":"karina_85@example.com","password":"Armenta85{@","name":"Karina Armenta"},
{"email":"agáta85@example.com","password":"Cesnak85^^","name":"Agáta Cesnak"},
{"email":"dorin_86@example.com","password":"Goldiș86^","name":"Dorin Goldiș"},
{"email":"İsmet_91@example.com","password":"Keskin91{\u0026","name":"İsmet Keskin"},
{"email":"aristița95@example.com","password":"Cadanțu95(%","name":"Aristița Cadanțu"},
{"email":"asya87@example.com","password":"Denizaşan87_(","name":"Asya Denizaşan"},
{"email":"slávka_87@example.com","password":"Šidlo87*#","name":"Slávka Šidlo"},
{"email":"段-磊@example.com","password":"磊87$^","name":"段 磊"},
{"email":"jordan_weber@example.com","password":"Weber93_@","name":"Jordan Weber"},
{"email":"Ιερώνυμος_87@example.com","password":"Αντωνοπούλου87%@","name":"Ιερώνυμος Αντωνοπούλου"},
{"email":"nora-90@example.com","password":"Rădescu90={","name":"Nora Rădescu"},
{"email":"tudor-90@example.com","password":"Dragoș90_=","name":"Tudor Dragoș"},
{"email":"paula-arroyo@example.com","password":"Arroyo98*\u0026","name":"Paula Arroyo"},
{"email":"jennifer-92@example.com","password":"Webb92^)","name":"Jennifer Webb"},
{"email":"hagymási-98@example.com","password":"Ágnes98\u0026{","name":"Hagymási Ágnes"},
{"email":"colin.weber@example.com","password":"Weber94=$","name":"Colin Weber"},
{"email":"laurian_84@example.com","password":"Oancea84=$","name":"Laurian Oancea"},
{"email":"luna-lebrun@example.com","password":"Lebrun87_}","name":"Luna Lebrun"},
{"email":"ion-98@example.com","password":"Blănculescu98@\u0026","name":"Ion Blănculescu"},
{"email":"iulia_lipă@example.com","password":"Lipă86==","name":"Iulia Lipă"},
{"email":"Ευαίων_95@example.com","password":"Μήτζου95%%","name":"Ευαίων Μήτζου"},
{"email":"Ángeles-gil@example.com","password":"Gil93)=","name":"Ángeles Gil"},
{"email":"timotej_98@example.com","password":"Paúk98#(","name":"Timotej Paúk"},
{"email":"sam-janssen@example.com","password":"Janssen93\u0026}","name":"Sam Janssen"},
{"email":"nurlanbek87@example.com","password":"Aliev87{{","name":"Nurlanbek Aliev"},
{"email":"dominika-85@example.com","password":"Chalupka85\u0026=","name":"Dominika Chalupka"},
{"email":"anghelina-94@example.com","password":"Dobrin94_}","name":"Anghelina Dobrin"},
{"email":"else_87@example.com","password":"Rønning87~^","name":"Else Rønning"},
{"email":"Галина_89@example.com","password":"ПАВЛОВ89*$","name":"Галина ПАВЛОВ"},
{"email":"dafina98@example.com","password":"Stănculescu98+#","name":"Dafina Stănculescu"},
{"email":"alicia-97@example.com","password":"Becerra97=*","name":"Alicia Becerra"},
{"email":"nicole85@example.com","password":"Wallace85$@","name":"Nicole Wallace"},
{"email":"eusebiu_89@example.com","password":"Honcescu89@@","name":"Eusebiu Honcescu"},
{"email":"leonardo-95@example.com","password":"Méndez95{=","name":"Leonardo Méndez"},
{"email":"usha-97@example.com","password":"Rajkarnikar97#\u0026","name":"Usha Rajkarnikar"},
{"email":"simona86@example.com","password":"Petrovický86~%","name":"Simona Petrovický"},
{"email":"mathis_97@example.com","password":"Dumont97~#","name":"Mathis Dumont"},
{"email":"mark-sanders@example.com","password":"Sanders88}}","name":"Mark Sanders"},
{"email":"Ασκάλαφος_93@example.com","password":"Παπαγεωργίου93~","name":"Ασκάλαφος Παπαγεωργίου"},
{"email":"liana84@example.com","password":"Grecescu84@@","name":"Liana Grecescu"},
{"email":"何_倰@example.com","password":"倰86@{","name":"何 倰"},
{"email":"-93@example.com","password":"فاطمهزهراطلوعی93#%","name":" فاطمه زهرا طلوعی"},
{"email":"otilia85@example.com","password":"Grigoriu85%!","name":"Otilia Grigoriu"},
{"email":"brândușa-87@example.com","password":"Cândea87#^","name":"Brândușa Cândea"},
{"email":"黎.辰@example.com","password":"辰92!","name":"黎 辰"},
{"email":"hilde-87@example.com","password":"Svendsen87*$","name":"Hilde Svendsen"},
{"email":"zdzisław_85@example.com","password":"Adamczyk85=#","name":"Zdzisław Adamczyk"},
{"email":"violeta.mumu@example.com","password":"Mumu85@{","name":"Violeta Mumu"},
{"email":"svetlana98@example.com","password":"Babka98@%","name":"Svetlana Babka"},
{"email":"tinca84@example.com","password":"Râpeanu84@","name":"Tinca Râpeanu"},
{"email":"Παναγιώτης-87@example.com","password":"Ελευθερίου87%_","name":"Παναγιώτης Ελευθερίου"},
{"email":"trương85@example.com","password":"Thương85*#","name":"Trương Thương"},
{"email":"Μεταγένης-86@example.com","password":"Λαγός86(@","name":"Μεταγένης Λαγός"},
{"email":"kaleb_illich@example.com","password":"Illich85~=","name":"Kaleb Illich"},
{"email":"ioan-90@example.com","password":"Ciocârlan90#%","name":"Ioan Ciocârlan"},
{"email":"colemusker@example.com","password":"Musker97^+","name":"Cole Musker"},
{"email":"luciana-97@example.com","password":"Honcescu97@=","name":"Luciana Honcescu"},
{"email":"askarali92@example.com","password":"Taalaibekov92#^","name":"Askarali Taalaibekov"},
{"email":"Μελέαγρος-84@example.com","password":"Δαγκλής84\u0026","name":"Μελέαγρος Δαγκλής"},
{"email":"kayla89@example.com","password":"Paquette89^(","name":"Kayla Paquette"},
{"email":"birat_kumal@example.com","password":"Kumal86(_","name":"Birat Kumal"},
{"email":"sabina_88@example.com","password":"Nottara88!_","name":"Sabina Nottara"},
{"email":"emanuel97@example.com","password":"Noica97**","name":"Emanuel Noica"},
{"email":"tatiana.tom@example.com","password":"Tom86}+","name":"Tatiana Tom"},
{"email":"romanița_86@example.com","password":"Costea86%^","name":"Romanița Costea"},
{"email":"antonia-95@example.com","password":"Șerbu95{+","name":"Antonia Șerbu"},
{"email":"Αχαιός_87@example.com","password":"Παπαϊωάννου87#","name":"Αχαιός Παπαϊωάννου"},
{"email":"Εύβουλος_85@example.com","password":"Βιλαέτης85}^","name":"Εύβουλος Βιλαέτης"},
{"email":"Христо-86@example.com","password":"АТАНАСОВ86*#","name":"Христо АТАНАСОВ"},
{"email":"Δημοφών_89@example.com","password":"Σαμαράς89$(","name":"Δημοφών Σαμαράς"},
{"email":"havasi.edina@example.com","password":"Edina89_%","name":"Havasi Edina"},
{"email":"marilena-96@example.com","password":"Oanca96+~","name":"Marilena Oanca"},
{"email":"alexandra-86@example.com","password":"Simon86_(","name":"Alexandra Simon"},
{"email":"sever-98@example.com","password":"Rusescu98__","name":"Sever Rusescu"},
{"email":"Αννα_98@example.com","password":"Μιαούλης98=+","name":"Αννα Μιαούλης"},
{"email":"lorena84@example.com","password":"Guzmán84}*","name":"Lorena Guzmán"},
{"email":"măriuca89@example.com","password":"Cucu89%+","name":"Măriuca Cucu"},
{"email":"田_朋@example.com","password":"朋93+_","name":"田 朋"},
{"email":"anda_96@example.com","password":"Ogăraru96%@","name":"Anda Ogăraru"},
{"email":"sárvári86@example.com","password":"Júlia86_+","name":"Sárvári Júlia"},
{"email":"arnold_88@example.com","password":"Machata88{=","name":"Arnold Machata"},
{"email":"angel-97@example.com","password":"Teleanu97(","name":"Angel Teleanu"},
{"email":"carmen_93@example.com","password":"Santiago93}","name":"Carmen Santiago"},
{"email":"mariedumont@example.com","password":"Dumont98((","name":"Marie Dumont"},
{"email":"daniel_85@example.com","password":"Pușcariu85+)","name":"Daniel Pușcariu"},
{"email":"adriána-84@example.com","password":"Šulc84)(","name":"Adriána Šulc"},
{"email":"Εφιάλτης_95@example.com","password":"Κοτζιάς95}{","name":"Εφιάλτης Κοτζιάς"},
{"email":"vasile89@example.com","password":"Celibidache89_^","name":"Vasile Celibidache"},
{"email":"丁_芳@example.com","password":"芳96=\u0026","name":"丁 芳"},
{"email":"marius_91@example.com","password":"Săvescu91~%","name":"Marius Săvescu"},
{"email":"bartolomeu87@example.com","password":"Șoitu87$$","name":"Bartolomeu Șoitu"},
{"email":"niculina98@example.com","password":"Sabău98}#","name":"Niculina Sabău"},
{"email":"daróczi_90@example.com","password":"Julianna90~~","name":"Daróczi Julianna"},
{"email":"Σωτήριος94@example.com","password":"Δοξαράς94=#","name":"Σωτήριος Δοξαράς"},
{"email":"joan_fowler@example.com","password":"Fowler93}!","name":"Joan Fowler"},
{"email":"kelly_87@example.com","password":"Richards87$\u0026","name":"Kelly Richards"},
{"email":"tiberia_97@example.com","password":"Nottara97*!","name":"Tiberia Nottara"},
{"email":"anna_stevens@example.com","password":"Stevens92**","name":"Anna Stevens"},
{"email":"philip97@example.com","password":"Contreras97^%","name":"Philip Contreras"},
{"email":"florica96@example.com","password":"Radovici96(*","name":"Florica Radovici"},
{"email":"Δαναός-98@example.com","password":"Καλαμογδάρτης98%","name":"Δαναός Καλαμογδάρτης"},
{"email":"leonard-98@example.com","password":"Kráľ98","name":"Leonard Kráľ"},
{"email":"paula92@example.com","password":"Bîrlădeanu92~+","name":"Paula Bîrlădeanu"},
{"email":"karolína_88@example.com","password":"Chalupka88\u0026_","name":"Karolína Chalupka"},
{"email":"denis_96@example.com","password":"Iepureanu96\u0026)","name":"Denis Iepureanu"},
{"email":"sofiahristu@example.com","password":"Hristu86+*","name":"Sofia Hristu"},
{"email":"aurel-88@example.com","password":"Podhradský88=","name":"Aurel Podhradský"},
{"email":"Ábrahám90@example.com","password":"Boglárka90)_","name":"Ábrahám Boglárka"},
{"email":"nicoleta-84@example.com","password":"Ciucurescu84)_","name":"Nicoleta Ciucurescu"},
{"email":"batuhan-96@example.com","password":"Yüksel96**","name":"Batuhan Yüksel"},
{"email":"ionel-85@example.com","password":"Cenușaru85%=","name":"Ionel Cenușaru"},
{"email":"Αριστοτέλης93@example.com","password":"Κουβέλης93!^","name":"Αριστοτέλης Κουβέλης"},
{"email":"nurtilek94@example.com","password":"Ismalilov94{(","name":"Nurtilek Ismalilov"},
{"email":"sandesh_89@example.com","password":"Ruchenbung89}(","name":"Sandesh Ruchenbung"},
{"email":"manju_95@example.com","password":"Tamrakar95+#","name":"Manju Tamrakar"},
{"email":"csopaki_92@example.com","password":"Bence92}!","name":"Csopaki Bence"},
{"email":"Ερμείας-86@example.com","password":"Ανδρέου86^_","name":"Ερμείας Ανδρέου"},
{"email":"bagi.nándor@example.com","password":"Nándor94*$","name":"Bagi Nándor"},
{"email":"vlastimil_91@example.com","password":"Šváby91~","name":"Vlastimil Šváby"},
{"email":"Želmíra92@example.com","password":"Krajči92#)","name":"Želmíra Krajči"},
{"email":"唐_花@example.com","password":"花84$","name":"唐 花"},
{"email":"sam88@example.com","password":"Richardson88%","name":"Sam Richardson"},
{"email":"willem94@example.com","password":"Hendriks94{(","name":"Willem Hendriks"},
{"email":"salvador_88@example.com","password":"González88%\u0026","name":"Salvador González"},
{"email":"vlaiculeca@example.com","password":"Leca91(\u0026","name":"Vlaicu Leca"},
{"email":"fikret-91@example.com","password":"Özkan91!=","name":"Fikret Özkan"},
{"email":"iasmina97@example.com","password":"Almaș97{(","name":"Iasmina Almaș"},
{"email":"angelo87@example.com","password":"Rinaldi87{#","name":"Angelo Rinaldi"},
{"email":"francisc-85@example.com","password":"Holda85@)","name":"Francisc Holda"},
{"email":"benito_98@example.com","password":"Camacho98_$","name":"Benito Camacho"},
{"email":"iolanda_87@example.com","password":"Slaivici87_#","name":"Iolanda Slaivici"},
{"email":"oľga-94@example.com","password":"Mikloš94@~","name":"Oľga Mikloš"},
{"email":"elena-mușat@example.com","password":"Mușat87~^","name":"Elena Mușat"},
{"email":"kristin-96@example.com","password":"Aasen96}^","name":"Kristin Aasen"},
{"email":"Κότυς-87@example.com","password":"Μήτζου87\u0026","name":"Κότυς Μήτζου"},
{"email":"eftimie-97@example.com","password":"Răceanu97$","name":"Eftimie Răceanu"},
{"email":"leana86@example.com","password":"Penescu86^","name":"Leana Penescu"},
{"email":"juliette-95@example.com","password":"Picard95${","name":"Juliette Picard"},
{"email":"samia-uddin@example.com","password":"Uddin87=","name":"Samia Uddin"},
{"email":"ariadna88@example.com","password":"Orășan88+~","name":"Ariadna Orășan"},
{"email":"Şükrü89@example.com","password":"Özgür89%@","name":"Şükrü Özgür"},
{"email":"esterapascu@example.com","password":"Pascu92@!","name":"Estera Pascu"},
{"email":"zekiye-97@example.com","password":"Kızılkaya97\u0026+","name":"Zekiye Kızılkaya"},
{"email":"Δαμέας_91@example.com","password":"Παπαϊωάννου91_!","name":"Δαμέας Παπαϊωάννου"},
{"email":"ottkangur@example.com","password":"Kangur86}_","name":"Ott Kangur"},
{"email":"amza-pacepa@example.com","password":"Pacepa91(","name":"Amza Pacepa"},
{"email":"Έλενα_84@example.com","password":"Ελευθερίου84#+","name":"Έλενα Ελευθερίου"},
{"email":"eusebiu85@example.com","password":"Catargi85\u0026!","name":"Eusebiu Catargi"},
{"email":"jean-pârvu@example.com","password":"Pârvu96**","name":"Jean Pârvu"},
{"email":"Şimay87@example.com","password":"Dikmen87){","name":"Şimay Dikmen"},
{"email":"Αρκάς94@example.com","password":"Λαμπρόπουλος94$%","name":"Αρκάς Λαμπρόπουλος"},
{"email":"遠藤_90@example.com","password":"陽翔90\u0026{","name":"遠藤 陽翔"},
{"email":"iurie88@example.com","password":"Vernescu88()","name":"Iurie Vernescu"},
{"email":"gajdi_rezső@example.com","password":"Rezső89_+","name":"Gajdi Rezső"},
{"email":"patricia96@example.com","password":"Filimon96!\u0026","name":"Patricia Filimon"},
{"email":"tristan94@example.com","password":"Poirier94{~","name":"Tristan Poirier"},
{"email":"sebők-94@example.com","password":"Aladár94@+","name":"Sebők Aladár"},
{"email":"franjo_98@example.com","password":"Mandić98!)","name":"Franjo Mandić"},
{"email":"eleonora-94@example.com","password":"Berindei94)#","name":"Eleonora Berindei"},
{"email":"samantha-86@example.com","password":"Cruz86#%","name":"Samantha Cruz"},
{"email":"annajones@example.com","password":"Jones88=","name":"Anna Jones"},
{"email":"juliette-85@example.com","password":"Cornelis85!","name":"Juliette Cornelis"},
{"email":"Μένων94@example.com","password":"Βαμβακάς94$@","name":"Μένων Βαμβακάς"},
{"email":"Ευρυμέδων_87@example.com","password":"Σπανού87=^","name":"Ευρυμέδων Σπανού"},
{"email":"Επειός-89@example.com","password":"Βενιζέλος89@~","name":"Επειός Βενιζέλος"},
{"email":"gregor93@example.com","password":"Korčák93%\u0026","name":"Gregor Korčák"},
{"email":"Ιάσονας-94@example.com","password":"Αλεξίου94\u0026","name":"Ιάσονας Αλεξίου"},
{"email":"bambang-85@example.com","password":"Dharmawan85\u0026","name":"Bambang Dharmawan"},
{"email":"Ľubomíra-88@example.com","password":"Melicherčík88{%","name":"Ľubomíra Melicherčík"},
{"email":"bobby.moore@example.com","password":"Moore89*@","name":"Bobby Moore"},
{"email":"Θρασύβουλος86@example.com","password":"Παπαστεφάνου86^_","name":"Θρασύβουλος Παπαστεφάνου"},
{"email":"flora95@example.com","password":"Crăciun95}%","name":"Flora Crăciun"},
{"email":"ხათუნა-94@example.com","password":"სურმანიძე94~$","name":"ხათუნა სურმანიძე"},
{"email":"benjamin-88@example.com","password":"Richard88++","name":"Benjamin Richard"},
{"email":"milan_thomas@example.com","password":"Thomas96{%","name":"Milan Thomas"},
{"email":"inès-collet@example.com","password":"Collet87}$","name":"Inès Collet"},
{"email":"坂本_87@example.com","password":"大輔87))","name":"坂本 大輔"},
{"email":"zenobia_86@example.com","password":"Blănculescu86\u0026=","name":"Zenobia Blănculescu"},
{"email":"ruszóhugó@example.com","password":"Hugó88#%","name":"Ruszó Hugó"},
{"email":"jasmine-87@example.com","password":"Clark87~\u0026","name":"Jasmine Clark"},
{"email":"petronela84@example.com","password":"Fedor84_{","name":"Petronela Fedor"},
{"email":"viorel97@example.com","password":"Pițurcă97{^","name":"Viorel Pițurcă"},
{"email":"liana97@example.com","password":"Grigoriu97~(","name":"Liana Grigoriu"},
{"email":"jaime_89@example.com","password":"Francisco89@*","name":"Jaime Francisco"},
{"email":"石-芯@example.com","password":"芯90^{","name":"石 芯"},
{"email":"aaroncalder@example.com","password":"Calder97\u0026@","name":"Aaron Calder"},
{"email":"ieremia93@example.com","password":"Buzescu93\u0026","name":"Ieremia Buzescu"},
{"email":"juan.collins@example.com","password":"Collins91@}","name":"Juan Collins"},
{"email":"blahoslav-89@example.com","password":"Bruška89+$","name":"Blahoslav Bruška"},
{"email":"marta_95@example.com","password":"Grigorieva95^~","name":"Marta Grigorieva"},
{"email":"iuliana92@example.com","password":"Căciulescu92^\u0026","name":"Iuliana Căciulescu"},
{"email":"simion_86@example.com","password":"Prelipceanu86^{","name":"Simion Prelipceanu"},
{"email":"andrada_86@example.com","password":"Seciu86%}","name":"Andrada Seciu"},
{"email":"joshua.khan@example.com","password":"Khan84}%","name":"Joshua Khan"},
{"email":"Μεταγένης_94@example.com","password":"Καλύβας94=(","name":"Μεταγένης Καλύβας"},
{"email":"Ηρακλής-87@example.com","password":"Νικολαΐδης87}^","name":"Ηρακλής Νικολαΐδης"},
{"email":"luciana-88@example.com","password":"Someșan88(=","name":"Luciana Someșan"},
{"email":"sarita-91@example.com","password":"Moktan91%)","name":"Sarita Moktan"},
{"email":"nərminə94@example.com","password":"Bəhramzadə94$@","name":"Nərminə Bəhramzadə"},
{"email":"carolina_85@example.com","password":"Berindei85\u0026=","name":"Carolina Berindei"},
{"email":"michal93@example.com","password":"Peško93%@","name":"Michal Peško"},
{"email":"Λαοδάμας-84@example.com","password":"Μιχαηλίδης84!~","name":"Λαοδάμας Μιχαηλίδης"},
{"email":"victoria-92@example.com","password":"Busch92(@","name":"Victoria Busch"},
{"email":"emanuele95@example.com","password":"Marino95%\u0026","name":"Emanuele Marino"},
{"email":"rachelbates@example.com","password":"Bates98~%","name":"Rachel Bates"},
{"email":"amalia_92@example.com","password":"Stavarache92~","name":"Amalia Stavarache"},
{"email":"alistar_95@example.com","password":"Pâslaru95@{","name":"Alistar Pâslaru"},
{"email":"corvin-89@example.com","password":"Popovici89$=","name":"Corvin Popovici"},
{"email":"ramiro94@example.com","password":"Paredes94{)","name":"Ramiro Paredes"},
{"email":"esad84@example.com","password":"Kolašinac84\u0026@","name":"Esad Kolašinac"},
{"email":"斎藤_92@example.com","password":"健太92}#","name":"斎藤 健太"},
{"email":"angelina89@example.com","password":"Murphy89!(","name":"Angelina Murphy"},
{"email":"nadyrbek-83@example.com","password":"Aliev83{)","name":"Nadyrbek Aliev"},
{"email":"julia-96@example.com","password":"Pădurean96)_","name":"Julia Pădurean"},
{"email":"rakonczai_86@example.com","password":"Sári86{{","name":"Rakonczai Sári"},
{"email":"nguyễn84@example.com","password":"Tân84{=","name":"Nguyễn Tân"},
{"email":"Εύανδρος87@example.com","password":"Ηλιόπουλος87#%","name":"Εύανδρος Ηλιόπουλος"},
{"email":"cristea89@example.com","password":"Nicoară89@*","name":"Cristea Nicoară"},
{"email":"victor89@example.com","password":"Gautier89\u0026","name":"Victor Gautier"},
{"email":"basarab-97@example.com","password":"Băsescu97(%","name":"Basarab Băsescu"},
{"email":"mairo.bala@example.com","password":"Bala87{\u0026","name":"Mairo Bala"},
{"email":"vladimíra_93@example.com","password":"Valenta93}^","name":"Vladimíra Valenta"},
{"email":"nyitrai-86@example.com","password":"Vilmos86@)","name":"Nyitrai Vilmos"},
{"email":"Λέων_93@example.com","password":"Βέργας93(*","name":"Λέων Βέργας"},
{"email":"ieremia89@example.com","password":"Popoviciu89\u0026=","name":"Ieremia Popoviciu"},
{"email":"klaudia_89@example.com","password":"Jančo89*%","name":"Klaudia Jančo"},
{"email":"dezider_91@example.com","password":"Ďurica91()","name":"Dezider Ďurica"},
{"email":"leah_84@example.com","password":"Mitchell84}=","name":"Leah Mitchell"},
{"email":"israel_85@example.com","password":"Cortez85*","name":"Israel Cortez"},
{"email":"Καλλίμαχος96@example.com","password":"Γιαννακόπουλος96*}","name":"Καλλίμαχος Γιαννακόπουλος"},
{"email":"celina-kühn@example.com","password":"Kühn93~","name":"Celina Kühn"},
{"email":"Θεόπομπος-96@example.com","password":"Κουβέλης96}!","name":"Θεόπομπος Κουβέλης"},
{"email":"Ιππόλυτος_87@example.com","password":"Βιλαέτης87%@","name":"Ιππόλυτος Βιλαέτης"},
{"email":"carmen_98@example.com","password":"Bădescu98${","name":"Carmen Bădescu"},
{"email":"alexis_moens@example.com","password":"Moens97)_","name":"Alexis Moens"},
{"email":"ناصر-92@example.com","password":"الشهراني92@!","name":"ناصر الشهراني"},
{"email":"camilmuraru@example.com","password":"Muraru94\u0026","name":"Camil Muraru"},
{"email":"axinte96@example.com","password":"Frențiu96~$","name":"Axinte Frențiu"},
{"email":"sara_deprez@example.com","password":"Deprez91_","name":"Sara Deprez"},
{"email":"augustin-89@example.com","password":"Bizău89~+","name":"Augustin Bizău"},
{"email":"isabell_96@example.com","password":"Neumann96!#","name":"Isabell Neumann"},
{"email":"공-수빈@example.com","password":"수빈85@@","name":"공 수빈"},
{"email":"melánia-96@example.com","password":"Matiaško96@@","name":"Melánia Matiaško"},
{"email":"võlan@example.com","password":"Lan85(~","name":"Võ Lan"},
{"email":"marcos.ríos@example.com","password":"Ríos98=","name":"Marcos Ríos"},
{"email":"sebastian_89@example.com","password":"Adams89$^","name":"Sebastian Adams"},
{"email":"oliver-93@example.com","password":"Mojžiš93!\u0026","name":"Oliver Mojžiš"},
{"email":"florența_87@example.com","password":"Lăzăreanu87#","name":"Florența Lăzăreanu"},
{"email":"harriet97@example.com","password":"Walker97(+","name":"Harriet Walker"},
{"email":"filip-89@example.com","password":"Vlachovič89%^","name":"Filip Vlachovič"},
{"email":"tinca.vâlcu@example.com","password":"Vâlcu92$#","name":"Tinca Vâlcu"},
{"email":"fabian96@example.com","password":"Tăbăraș96\u0026","name":"Fabian Tăbăraș"},
{"email":"Αρχίας_86@example.com","password":"Θεοδοσίου86@\u0026","name":"Αρχίας Θεοδοσίου"},
{"email":"désirée-95@example.com","password":"Colin95=#","name":"Désirée Colin"},
{"email":"mia_98@example.com","password":"Robertson98\u0026}","name":"Mia Robertson"},
{"email":"ghenadie87@example.com","password":"Costea87#~","name":"Ghenadie Costea"},
{"email":"josephine94@example.com","password":"Fuchs94$(","name":"Josephine Fuchs"},
{"email":"abdurrahman-85@example.com","password":"Terman85*{","name":"Abdurrahman Terman"},
{"email":"eftimia_87@example.com","password":"Pîrvu87*_","name":"Eftimia Pîrvu"},
{"email":"dipendra95@example.com","password":"Dulal95\u0026%","name":"Dipendra Dulal"},
{"email":"zamfir-87@example.com","password":"Paleru87_\u0026","name":"Zamfir Paleru"},
{"email":"paula-salas@example.com","password":"Salas97%$","name":"Paula Salas"},
{"email":"martín97@example.com","password":"Crespo97%(","name":"Martín Crespo"},
{"email":"ernst van_85@example.com","password":"Dam85_}","name":"Ernst van Dam"},
{"email":"苏.思@example.com","password":"思87(*","name":"苏 思"},
{"email":"ნოდარ-94@example.com","password":"ცეცხლაძე94*$","name":"ნოდარ ცეცხლაძე"},
{"email":"alice93@example.com","password":"Morrison93$#","name":"Alice Morrison"},
{"email":"márton91@example.com","password":"Kornél91^#","name":"Márton Kornél"},
{"email":"perla_84@example.com","password":"Šimonovič84{{","name":"Perla Šimonovič"},
{"email":"gyimesi-ede@example.com","password":"Ede96}*","name":"Gyimesi Ede"},
{"email":"franziska85@example.com","password":"Pfeiffer85++","name":"Franziska Pfeiffer"},
{"email":"georgiana_96@example.com","password":"Păcurariu96!=","name":"Georgiana Păcurariu"},
{"email":"aaron_rey@example.com","password":"Rey94+_","name":"Aaron Rey"},
{"email":"zeno-86@example.com","password":"Pușcariu86)~","name":"Zeno Pușcariu"},
{"email":"-85@example.com","password":"JuanJoséMartín85@}","name":" Juan José Martín"},
{"email":"fehérvári90@example.com","password":"Zsolt90}}","name":"Fehérvári Zsolt"},
{"email":"norbert90@example.com","password":"Bărlea90{_","name":"Norbert Bărlea"},
{"email":"fábián98@example.com","password":"Márk98+!","name":"Fábián Márk"},
{"email":"Εύανδρος-96@example.com","password":"Δουμπιώτης96~%","name":"Εύανδρος Δουμπιώτης"},
{"email":"melih_96@example.com","password":"Güğül96{*","name":"Melih Güğül"},
{"email":"tillstein@example.com","password":"Stein91\u0026_","name":"Till Stein"},
{"email":"gyimesi_95@example.com","password":"Letti95~@","name":"Gyimesi Letti"},
{"email":"tayla87@example.com","password":"Stanton87%*","name":"Tayla Stanton"},
{"email":"falusi_84@example.com","password":"Julianna84){","name":"Falusi Julianna"},
{"email":"Διαγόρας_89@example.com","password":"Κοντολέων89!{","name":"Διαγόρας Κοντολέων"},
{"email":"tudorița-94@example.com","password":"Macovei94*(","name":"Tudorița Macovei"},
{"email":"madan_bamjan@example.com","password":"Bamjan92#$","name":"Madan Bamjan"},
{"email":"向蕾@example.com","password":"蕾90!_","name":"向 蕾"},
{"email":"jacob_murray@example.com","password":"Murray97{@","name":"Jacob Murray"},
{"email":"پرهام_87@example.com","password":"عبدالعلی87*^","name":"پرهام عبدالعلی"},
{"email":"dorin83@example.com","password":"Negreanu83{{","name":"Dorin Negreanu"},
{"email":"ruxandra-85@example.com","password":"Giulian85{=","name":"Ruxandra Giulian"},
{"email":"蔡.茂@example.com","password":"茂94$*","name":"蔡 茂"},
{"email":"دانیال96@example.com","password":"زارع96*\u0026","name":"دانیال زارع"},
{"email":"eva depauw@example.com","password":"Pauw95((","name":"Eva De Pauw"},
{"email":"jorge-díaz@example.com","password":"Díaz86^)","name":"Jorge Díaz"},
{"email":"cornelia_86@example.com","password":"Coteanu86(^","name":"Cornelia Coteanu"},
{"email":"luiza.hanu@example.com","password":"Hanu94~~","name":"Luiza Hanu"},
{"email":"sorina93@example.com","password":"Soltan93@}","name":"Sorina Soltan"},
{"email":"zaharia-88@example.com","password":"Preda88~~","name":"Zaharia Preda"},
{"email":"minodora87@example.com","password":"Ghinea87(^","name":"Minodora Ghinea"},
{"email":"marcos87@example.com","password":"Herrera87\u0026","name":"Marcos Herrera"},
{"email":"Μεταγένης_91@example.com","password":"Λούλης91{(","name":"Μεταγένης Λούλης"},
{"email":"lương_96@example.com","password":"Thụ96!*","name":"Lương Thụ"},
{"email":"viorel_89@example.com","password":"Varzar89^%","name":"Viorel Varzar"},
{"email":"slavomír-92@example.com","password":"Valachovič92)%","name":"Slavomír Valachovič"},
{"email":"andrew_86@example.com","password":"Castro86#{","name":"Andrew Castro"},
{"email":"Μένων_97@example.com","password":"Φιλιππίδης97^=","name":"Μένων Φιλιππίδης"},
{"email":"mark.white@example.com","password":"White92)}","name":"Mark White"},
{"email":"subash-85@example.com","password":"Pradhanang85~=","name":"Subash Pradhanang"},
{"email":"ludovica94@example.com","password":"Hațiegan94$%","name":"Ludovica Hațiegan"},
{"email":"elvira-92@example.com","password":"Ventura92*(","name":"Elvira Ventura"},
{"email":"ayodeji86@example.com","password":"Kabir86%(","name":"Ayodeji Kabir"},
{"email":"astrid de la-96@example.com","password":"Marina96{+","name":"Astrid De la Marina"},
{"email":"anthony_97@example.com","password":"Hopkins97\u0026$","name":"Anthony Hopkins"},
{"email":"linda98@example.com","password":"Stodola98*{","name":"Linda Stodola"},
{"email":"blažej85@example.com","password":"Kozáček85=@","name":"Blažej Kozáček"},
{"email":"wágner.ede@example.com","password":"Ede90{^","name":"Wágner Ede"},
{"email":"flora-buhuș@example.com","password":"Buhuș89{+","name":"Flora Buhuș"},
{"email":"Φαίδιμος-96@example.com","password":"Αξιώτης96}{","name":"Φαίδιμος Αξιώτης"},
{"email":"arapbay_92@example.com","password":"Zharkynbaiev92##","name":"Arapbay Zharkynbaiev"},
{"email":"Σταμάτης_88@example.com","password":"Ανδρέου88)%","name":"Σταμάτης Ανδρέου"},
{"email":"lázi89@example.com","password":"Bendegúz89$$","name":"Lázi Bendegúz"},
{"email":"Δάρδανος-93@example.com","password":"Μπότσαρης93^(","name":"Δάρδανος Μπότσαρης"},
{"email":"renata_96@example.com","password":"Almașanu96)$","name":"Renata Almașanu"},
{"email":"Μόψος96@example.com","password":"Δασκαλοπούλου96@^","name":"Μόψος Δασκαλοπούλου"},
{"email":"hứa_khang@example.com","password":"Khang97{*","name":"Hứa Khang"},
{"email":"sidhant_85@example.com","password":"Bhumi85~","name":"Sidhant Bhumi"},
{"email":"marie.knight@example.com","password":"Knight84$$","name":"Marie Knight"},
{"email":"daria91@example.com","password":"Lăzăreanu91_!","name":"Daria Lăzăreanu"},
{"email":"pranavyadav@example.com","password":"Yadav91_(","name":"Pranav Yadav"},
{"email":"marwane-94@example.com","password":"Garcia94}~","name":"Marwane Garcia"},
{"email":"오.정숙@example.com","password":"정숙87}(","name":"오 정숙"},
{"email":"rózsahegyi84@example.com","password":"Jakab84_~","name":"Rózsahegyi Jakab"},
{"email":"mã.khải@example.com","password":"Khải95{~","name":"Mã Khải"},
{"email":"Ελλάδιος_85@example.com","password":"Λούπης85~!","name":"Ελλάδιος Λούπης"},
{"email":"Հակոբ-85@example.com","password":"Շահինյան85=*","name":"Հակոբ Շահինյան"},
{"email":"petrișor_90@example.com","password":"Crăciun90$@","name":"Petrișor Crăciun"},
{"email":"adelina-88@example.com","password":"Panțuru88}+","name":"Adelina Panțuru"},
{"email":"necdet-88@example.com","password":"Özbek88=}","name":"Necdet Özbek"},
{"email":"sophie-93@example.com","password":"Davies93{^","name":"Sophie Davies"},
{"email":"alžbeta_94@example.com","password":"Konrád94(}","name":"Alžbeta Konrád"},
{"email":"Ιερεμίας_94@example.com","password":"Δεσποτόπουλος94~$","name":"Ιερεμίας Δεσποτόπουλος"},
{"email":"Δημοφών-91@example.com","password":"Δουρέντης91~","name":"Δημοφών Δουρέντης"},
{"email":"hoàng.dũng@example.com","password":"Dũng87({","name":"Hoàng Dũng"},
{"email":"sidhant91@example.com","password":"Kafle91@@","name":"Sidhant Kafle"},
{"email":"recai94@example.com","password":"Üstündaş94!(","name":"Recai Üstündaş"},
{"email":"melania_84@example.com","password":"Bucurescu84^_","name":"Melania Bucurescu"},
{"email":"hegedűs97@example.com","password":"Lázár97~%","name":"Hegedűs Lázár"},
{"email":"sharada-91@example.com","password":"Lungeli91{*","name":"Sharada Lungeli"},
{"email":"Șerban85@example.com","password":"Vatamanu85\u0026~","name":"Șerban Vatamanu"},
{"email":"erlan-imanov@example.com","password":"Imanov94(}","name":"Erlan Imanov"},
{"email":"steven-86@example.com","password":"Larson86$(","name":"Steven Larson"},
{"email":"ofelia-90@example.com","password":"Barrios90*{","name":"Ofelia Barrios"},
{"email":"Žofiabača@example.com","password":"Bača85$^","name":"Žofia Bača"},
{"email":"csonka_93@example.com","password":"Lenóra93}$","name":"Csonka Lenóra"},
{"email":"vanesa-95@example.com","password":"Štefanko95\u0026$","name":"Vanesa Štefanko"},
{"email":"-86@example.com","password":"JoséAngelArriaga86*_","name":" José Angel Arriaga"},
{"email":"olav94@example.com","password":"Halvorsen94^$","name":"Olav Halvorsen"},
{"email":"haralambie94@example.com","password":"Ciortea94#)","name":"Haralambie Ciortea"},
{"email":"alin-97@example.com","password":"Filipescu97+^","name":"Alin Filipescu"},
{"email":"florian-97@example.com","password":"Hamon97_!","name":"Florian Hamon"},
{"email":"olivia_vera@example.com","password":"Vera88!~","name":"Olivia Vera"},
{"email":"Κλεινίας-97@example.com","password":"Δυοβουνιώτης97+_","name":"Κλεινίας Δυοβουνιώτης"},
{"email":"delphine97@example.com","password":"Dupont97}\u0026","name":"Delphine Dupont"},
{"email":"Žofia-rišo@example.com","password":"Rišo91^$","name":"Žofia Rišo"},
{"email":"Павлина92@example.com","password":"КОЛЕВА92{","name":"Павлина КОЛЕВА"},
{"email":"87@example.com","password":"MaríaIsabelGiménez87)}","name":" María Isabel Giménez"},
{"email":"augustín_90@example.com","password":"Huba90^","name":"Augustín Huba"},
{"email":"vona89@example.com","password":"Gabriella89+_","name":"Vona Gabriella"},
{"email":"Μίμας_85@example.com","password":"Ταμτάκος85#{","name":"Μίμας Ταμτάκος"},
{"email":"barchyngul-97@example.com","password":"Kushbekov97^=","name":"Barchyngul Kushbekov"},
{"email":"roberta-92@example.com","password":"Argetoianu92++","name":"Roberta Argetoianu"},
{"email":"alessandra93@example.com","password":"Gallo93__","name":"Alessandra Gallo"},
{"email":"greta.ludwig@example.com","password":"Ludwig86@^","name":"Greta Ludwig"},
{"email":"lýdia98@example.com","password":"Malíšek98!%","name":"Lýdia Malíšek"},
{"email":"杨-瑞@example.com","password":"瑞87{=","name":"杨 瑞"},
{"email":"Ευκτήμων_89@example.com","password":"Πολίτης89^{","name":"Ευκτήμων Πολίτης"},
{"email":"christian_98@example.com","password":"Freeman98}}","name":"Christian Freeman"},
{"email":"vedat_vural@example.com","password":"Vural95+#","name":"Vedat Vural"},
{"email":"enes93@example.com","password":"Salihović93\u0026)","name":"Enes Salihović"},
{"email":"lolapetit@example.com","password":"Petit98_!","name":"Lola Petit"},
{"email":"aleš_96@example.com","password":"Durdík96!~","name":"Aleš Durdík"},
{"email":"Λεωνίδας91@example.com","password":"Λύτρας91%\u0026","name":"Λεωνίδας Λύτρας"},
{"email":"david-95@example.com","password":"Stewart95=(","name":"David Stewart"},
{"email":"janet96@example.com","password":"Franklin96_}","name":"Janet Franklin"},
{"email":"hortenzia-94@example.com","password":"Bukovský94^_","name":"Hortenzia Bukovský"},
{"email":"amelbaljić@example.com","password":"Baljić85=","name":"Amel Baljić"},
{"email":"zoja_kráľ@example.com","password":"Kráľ84+\u0026","name":"Zoja Kráľ"},
{"email":"Εύηνος_91@example.com","password":"Ζάχος91(!","name":"Εύηνος Ζάχος"},
{"email":"sten89@example.com","password":"Nikolaev89+","name":"Sten Nikolaev"},
{"email":"julio-ríos@example.com","password":"Ríos87)(","name":"Julio Ríos"},
{"email":"dilay96@example.com","password":"Türkcan96(","name":"Dilay Türkcan"},
{"email":"violeta_87@example.com","password":"Țîrle87(~","name":"Violeta Țîrle"},
{"email":"cezar-97@example.com","password":"Avramescu97%#","name":"Cezar Avramescu"},
{"email":"fekete98@example.com","password":"Rezső98(%","name":"Fekete Rezső"},
{"email":"Δαμιανός88@example.com","password":"Κυπραίος88=*","name":"Δαμιανός Κυπραίος"},
{"email":"kanalas_91@example.com","password":"Anita91$","name":"Kanalas Anita"},
{"email":"Φαίδιμος88@example.com","password":"Τομαραίοι88#%","name":"Φαίδιμος Τομαραίοι"},
{"email":"Εύηνος_89@example.com","password":"Βιτάλης89\u0026\u0026","name":"Εύηνος Βιτάλης"},
{"email":"ghenadie91@example.com","password":"Buzoianu91}#","name":"Ghenadie Buzoianu"},
{"email":"horațiu_88@example.com","password":"Cîmpeanu88^!","name":"Horațiu Cîmpeanu"},
{"email":"makra_92@example.com","password":"Xaviér92#+","name":"Makra Xaviér"},
{"email":"sudha_89@example.com","password":"Koirala89\u0026}","name":"Sudha Koirala"},
{"email":"anabela88@example.com","password":"Hraško88@","name":"Anabela Hraško"},
{"email":"iridenta_86@example.com","password":"Djuvara86)","name":"Iridenta Djuvara"},
{"email":"marinela91@example.com","password":"Bratu91^(","name":"Marinela Bratu"},
{"email":"iasmina-92@example.com","password":"Ulmeanu92}}","name":"Iasmina Ulmeanu"},
{"email":"aglaia-93@example.com","password":"Călinescu93*%","name":"Aglaia Călinescu"},
{"email":"iasmina-85@example.com","password":"Greceanu85\u0026","name":"Iasmina Greceanu"},
{"email":"marcela_87@example.com","password":"Valušek87}@","name":"Marcela Valušek"},
{"email":"eremia-85@example.com","password":"Berindei85\u0026%","name":"Eremia Berindei"},
{"email":"olivia86@example.com","password":"Răducan86*)","name":"Olivia Răducan"},
{"email":"georgeta-96@example.com","password":"Berindei96(}","name":"Georgeta Berindei"},
{"email":"Петър84@example.com","password":"АЛЕКСАНДРОВ84_=","name":"Петър АЛЕКСАНДРОВ"},
{"email":"harkai96@example.com","password":"Szilveszter96\u0026#","name":"Harkai Szilveszter"},
{"email":"Διογένης-84@example.com","password":"Κουντουριώτης84@)","name":"Διογένης Κουντουριώτης"},
{"email":"Λύκος91@example.com","password":"Παππάς91@_","name":"Λύκος Παππάς"},
{"email":"Γεννάδιος94@example.com","password":"Δελή94}~","name":"Γεννάδιος Δελή"},
{"email":"Εύρυτος_91@example.com","password":"Οικονόμου91@%","name":"Εύρυτος Οικονόμου"},
{"email":"ionel-93@example.com","password":"Bănică93!","name":"Ionel Bănică"},
{"email":"codylowe@example.com","password":"Lowe95+^","name":"Cody Lowe"},
{"email":"schneider91@example.com","password":"Szofi91~\u0026","name":"Schneider Szofi"},
{"email":"Ερμής-95@example.com","password":"Νικολάκος95#!","name":"Ερμής Νικολάκος"},
{"email":"martin_90@example.com","password":"Neculce90}^","name":"Martin Neculce"},
{"email":"marabarna@example.com","password":"Barna94=}","name":"Mara Barna"},
{"email":"Ικέτας_95@example.com","password":"Αθανασιάδης95%%","name":"Ικέτας Αθανασιάδης"},
{"email":"ninasmet@example.com","password":"Smet84}#","name":"Nina Smet"},
{"email":"rafel84@example.com","password":"Văsescu84)@","name":"Rafel Văsescu"},
{"email":"noel.shyti@example.com","password":"Shyti91!~","name":"Noel Shyti"},
{"email":"teodosia84@example.com","password":"Angelescu84#{","name":"Teodosia Angelescu"},
{"email":"mason-scott@example.com","password":"Scott91(","name":"Mason Scott"},
{"email":"emilia_98@example.com","password":"Captaru98\u0026)","name":"Emilia Captaru"},
{"email":"györki-96@example.com","password":"Péter96})","name":"Györki Péter"},
{"email":"francisco_84@example.com","password":"Cortés84=}","name":"Francisco Cortés"},
{"email":"Ιάσονας89@example.com","password":"Παπακωνσταντίνου89%#","name":"Ιάσονας Παπακωνσταντίνου"},
{"email":"giorgian85@example.com","password":"Suceveanu85+*","name":"Giorgian Suceveanu"},
{"email":"henrich89@example.com","password":"Cesnak89##","name":"Henrich Cesnak"},
{"email":"luca.moens@example.com","password":"Moens95\u0026$","name":"Luca Moens"},
{"email":"severin_87@example.com","password":"Sorescu87}(","name":"Severin Sorescu"},
{"email":"ivana_97@example.com","password":"Majeský97}","name":"Ivana Majeský"},
{"email":"majzik_Éva@example.com","password":"Éva92@^","name":"Majzik Éva"},
{"email":"valentin_89@example.com","password":"Iaru89=@","name":"Valentin Iaru"},
{"email":"corneliu_95@example.com","password":"Miclea95_~","name":"Corneliu Miclea"},
{"email":"noelbrahimi@example.com","password":"Brahimi93!)","name":"Noel Brahimi"},
{"email":"eduardo_92@example.com","password":"Moreno92!$","name":"Eduardo Moreno"},
{"email":"juliaríos@example.com","password":"Ríos87^{","name":"Julia Ríos"},
{"email":"helena_92@example.com","password":"Kozáčik92!","name":"Helena Kozáčik"},
{"email":"adelin_97@example.com","password":"Moculescu97$^","name":"Adelin Moculescu"},
{"email":"isaac_90@example.com","password":"Robertson90)\u0026","name":"Isaac Robertson"},
{"email":"silvia90@example.com","password":"Buzoianu90_}","name":"Silvia Buzoianu"},
{"email":"은채원@example.com","password":"채원88^$","name":"은 채원"},
{"email":"măriuca-98@example.com","password":"Suceveanu98^)","name":"Măriuca Suceveanu"},
{"email":"田姗@example.com","password":"姗96=@","name":"田 姗"},
{"email":"alida90@example.com","password":"Călugăreanu90!_","name":"Alida Călugăreanu"},
{"email":"iuliana_85@example.com","password":"Captaru85{_","name":"Iuliana Captaru"},
{"email":"zamfira-90@example.com","password":"Almaș90{!","name":"Zamfira Almaș"},
{"email":"岡本_92@example.com","password":"心愛92~%","name":"岡本 心愛"},
{"email":"Ιαπετός-84@example.com","password":"Βενιζέλος84(@","name":"Ιαπετός Βενιζέλος"},
{"email":"rabindra-84@example.com","password":"Kandel84${","name":"Rabindra Kandel"},
{"email":"münir-90@example.com","password":"Demirkol90@_","name":"Münir Demirkol"},
{"email":"-87@example.com","password":"JoséFranciscoCortés87=)","name":" José Francisco Cortés"},
{"email":"gențiana_86@example.com","password":"Averescu86}~","name":"Gențiana Averescu"},
{"email":"أريج-90@example.com","password":"السعيد90=~","name":"أريج السعيد"},
{"email":"arina-94@example.com","password":"Vicovean94}_","name":"Arina Vicovean"},
{"email":"Γλαύκος93@example.com","password":"Καλύβας93=}","name":"Γλαύκος Καλύβας"},
{"email":"rita_91@example.com","password":"Budathoki91{}","name":"Rita Budathoki"},
{"email":"nisan.yiğit@example.com","password":"Yiğit87+","name":"Nisan Yiğit"},
{"email":"متین-96@example.com","password":"نامور96%","name":"متین نامور"},
{"email":"dora-92@example.com","password":"Văluță92_+","name":"Dora Văluță"},
{"email":"zádori-93@example.com","password":"Cintia93$","name":"Zádori Cintia"},
{"email":"durga_regmi@example.com","password":"Regmi96(_","name":"Durga Regmi"},
{"email":"aureliana_95@example.com","password":"Velescu95_*","name":"Aureliana Velescu"},
{"email":"Γεράσιμος-96@example.com","password":"Κορνάρος96^=","name":"Γεράσιμος Κορνάρος"},
{"email":"julianweiß@example.com","password":"Weiß87{!","name":"Julian Weiß"},
{"email":"estera88@example.com","password":"Bukovský88(","name":"Estera Bukovský"},
{"email":"dinu.livescu@example.com","password":"Livescu93#","name":"Dinu Livescu"},
{"email":"Ľubomíra-92@example.com","password":"Truban92_}","name":"Ľubomíra Truban"},
{"email":"isidro_94@example.com","password":"Ramírez94=^","name":"Isidro Ramírez"},
{"email":"zsolnai_pál@example.com","password":"Pál94!@","name":"Zsolnai Pál"},
{"email":"félix96@example.com","password":"Ďuriš96!^","name":"Félix Ďuriš"},
{"email":"bronislava_95@example.com","password":"Kolník95!%","name":"Bronislava Kolník"},
{"email":"florentin_87@example.com","password":"Marie87%$","name":"Florentin Marie"},
{"email":"eva85@example.com","password":"Βλαχόπουλος85_^","name":"Eva Βλαχόπουλος"},
{"email":"marga-88@example.com","password":"Olinescu88=~","name":"Marga Olinescu"},
{"email":"النا_93@example.com","password":"ایروانی93!%","name":"النا ایروانی"},
{"email":"arnaud.simon@example.com","password":"Simon95=$","name":"Arnaud Simon"},
{"email":"hayden.smart@example.com","password":"Smart91!","name":"Hayden Smart"},
{"email":"henrieta97@example.com","password":"Melicherčík97!@","name":"Henrieta Melicherčík"},
{"email":"candice_96@example.com","password":"Riviere96}#","name":"Candice Riviere"},
{"email":"doriana98@example.com","password":"Livescu98*^","name":"Doriana Livescu"},
{"email":"mándi_92@example.com","password":"Csilla92%!","name":"Mándi Csilla"},
{"email":"reuben_83@example.com","password":"Aldridge83(*","name":"Reuben Aldridge"},
{"email":"elinledin@example.com","password":"Ledin91^*","name":"Elin Ledin"},
{"email":"sean-moth@example.com","password":"Moth89)\u0026","name":"Sean Moth"},
{"email":"Γανυμήδης-87@example.com","password":"Αθανασιάδης87{@","name":"Γανυμήδης Αθανασιάδης"},
{"email":"Δημόδοκος-90@example.com","password":"Κομνηνός90~@","name":"Δημόδοκος Κομνηνός"},
{"email":"emil_90@example.com","password":"Tomečko90#~","name":"Emil Tomečko"},
{"email":"emily-sims@example.com","password":"Sims98+)","name":"Emily Sims"},
{"email":"antónia-97@example.com","password":"Dusík97__","name":"Antónia Dusík"},
{"email":"doriana_84@example.com","password":"Popovici84!)","name":"Doriana Popovici"},
{"email":"vlastimil91@example.com","password":"Marcinek91+*","name":"Vlastimil Marcinek"},
{"email":"jarolím97@example.com","password":"Mišík97\u0026*","name":"Jarolím Mišík"},
{"email":"cosmina-98@example.com","password":"Turcdeanu98+*","name":"Cosmina Turcdeanu"},
{"email":"boris87@example.com","password":"Miklík87^!","name":"Boris Miklík"},
{"email":"savina_95@example.com","password":"Lăzărescu95@","name":"Savina Lăzărescu"},
{"email":"eylül95@example.com","password":"Denizaşan95@+","name":"Eylül Denizaşan"},
{"email":"ieremia96@example.com","password":"Cenușaru96%~","name":"Ieremia Cenușaru"},
{"email":"thiago_94@example.com","password":"Rodríguez94#{","name":"Thiago Rodríguez"},
{"email":"galina-ján@example.com","password":"Ján88}\u0026","name":"Galina Ján"},
{"email":"balogh_89@example.com","password":"Viktória89!)","name":"Balogh Viktória"},
{"email":"ebru-güneş@example.com","password":"Güneş98_(","name":"Ebru Güneş"},
{"email":"atena-92@example.com","password":"Dragoș92\u0026","name":"Atena Dragoș"},
{"email":"سجاد_98@example.com","password":"نعمتی98!#","name":"سجاد نعمتی"},
{"email":"erős_péter@example.com","password":"Péter92*#","name":"Erős Péter"},
{"email":"Ερμής96@example.com","password":"Αλεξανδρίδης96~+","name":"Ερμής Αλεξανδρίδης"},
{"email":"malvina93@example.com","password":"Rosetti93%(","name":"Malvina Rosetti"},
{"email":"rıdvan93@example.com","password":"Özkes93*$","name":"Rıdvan Özkes"},
{"email":"jack_hardy@example.com","password":"Hardy87{~","name":"Jack Hardy"},
{"email":"bernard86@example.com","password":"Marko86}*","name":"Bernard Marko"},
{"email":"Ελισσώνας_93@example.com","password":"Παπακώστας93%\u0026","name":"Ελισσώνας Παπακώστας"},
{"email":"Εχεκράτης-83@example.com","password":"Ζωγράφου83!%","name":"Εχεκράτης Ζωγράφου"},
{"email":"mara.varzar@example.com","password":"Varzar89^+","name":"Mara Varzar"},
{"email":"tibor_89@example.com","password":"Líška89)*","name":"Tibor Líška"},
{"email":"Зинаида-86@example.com","password":"Ротару86+{","name":"Зинаида Ротару"},
{"email":"aurora_89@example.com","password":"Neacșu89)","name":"Aurora Neacșu"},
{"email":"mária-87@example.com","password":"Plešivec87)^","name":"Mária Plešivec"},
{"email":"dagmara-kuba@example.com","password":"Kuba92*$","name":"Dagmara Kuba"},
{"email":"tarmo_orav@example.com","password":"Orav95_(","name":"Tarmo Orav"},
{"email":"monica-86@example.com","password":"Găitan86\u0026","name":"Monica Găitan"},
{"email":"diana-86@example.com","password":"Correia86%+","name":"Diana Correia"},
{"email":"adelin-90@example.com","password":"Bîrlădeanu90=)","name":"Adelin Bîrlădeanu"},
{"email":"akriti-bhatt@example.com","password":"Bhatt85=)","name":"Akriti Bhatt"},
{"email":"dylan-reyes@example.com","password":"Reyes86!^","name":"Dylan Reyes"},
{"email":"Γλαύκος-94@example.com","password":"Παππάς94{!","name":"Γλαύκος Παππάς"},
{"email":"achim89@example.com","password":"Dobrescu89@\u0026","name":"Achim Dobrescu"},
{"email":"ainar-87@example.com","password":"Samaghanov87~_","name":"Ainar Samaghanov"},
{"email":"rocío_92@example.com","password":"Arredondo92()","name":"Rocío Arredondo"},
{"email":"ahenk-Şirin@example.com","password":"Şirin84*^","name":"Ahenk Şirin"},
{"email":"손-정숙@example.com","password":"정숙98$+","name":"손 정숙"},
{"email":"eusebiu-95@example.com","password":"Orășan95\u0026","name":"Eusebiu Orășan"},
{"email":"kanti95@example.com","password":"Chandra95%+","name":"Kanti Chandra"},
{"email":"voichița_94@example.com","password":"Filipescu94~$","name":"Voichița Filipescu"},
{"email":"marcela92@example.com","password":"Ornea92_}","name":"Marcela Ornea"},
{"email":"marcugoga@example.com","password":"Goga89_(","name":"Marcu Goga"},
{"email":"97@example.com","password":"JoséLuisJaramillo97!~","name":" José Luis Jaramillo"},
{"email":"petrică-88@example.com","password":"Olănescu88_@","name":"Petrică Olănescu"},
{"email":"deák97@example.com","password":"Gergely97#","name":"Deák Gergely"},
{"email":"douglas-93@example.com","password":"Vasquez93=","name":"Douglas Vasquez"},
{"email":"petrică_88@example.com","password":"Budeanu88~_","name":"Petrică Budeanu"},
{"email":"Ευβουλέας87@example.com","password":"Παπανικολάου87($","name":"Ευβουλέας Παπανικολάου"},
{"email":"chandrakala87@example.com","password":"Prajapati87%^","name":"Chandrakala Prajapati"},
{"email":"mildred.reid@example.com","password":"Reid87#{","name":"Mildred Reid"},
{"email":"hajas92@example.com","password":"Barbara92(}","name":"Hajas Barbara"},
{"email":"Ανδρέας_90@example.com","password":"Αργυριάδης90}#","name":"Ανδρέας Αργυριάδης"},
{"email":"diana96@example.com","password":"Masaryk96)%","name":"Diana Masaryk"},
{"email":"ligia_bogos@example.com","password":"Bogos89#","name":"Ligia Bogos"},
{"email":"Κρατερός-97@example.com","password":"Ρόκας97{#","name":"Κρατερός Ρόκας"},
{"email":"serhan_93@example.com","password":"Erdoğan93$@","name":"Serhan Erdoğan"},
{"email":"sandra_90@example.com","password":"Männik90{!","name":"Sandra Männik"},
{"email":"yogesh89@example.com","password":"Pulami89*{","name":"Yogesh Pulami"},
{"email":"jámbor86@example.com","password":"Júlia86\u0026(","name":"Jámbor Júlia"},
{"email":"anna-ali@example.com","password":"Ali92$~","name":"Anna Ali"},
{"email":"_95@example.com","password":"JoséGuadalupeSosa95%#","name":" José Guadalupe Sosa"},
{"email":"rozália_96@example.com","password":"Capek96^!","name":"Rozália Capek"},
{"email":"Δαναός_89@example.com","password":"Ταμτάκος89)_","name":"Δαναός Ταμτάκος"},
{"email":"phạm_89@example.com","password":"Triết89{#","name":"Phạm Triết"},
{"email":"flynn-89@example.com","password":"Stanton89_}","name":"Flynn Stanton"},
{"email":"delia-98@example.com","password":"Toduță98_","name":"Delia Toduță"},
{"email":"mándi.detti@example.com","password":"Detti98\u0026=","name":"Mándi Detti"},
{"email":"Ευτρόπιος98@example.com","password":"Μαγγίνας98\u0026\u0026","name":"Ευτρόπιος Μαγγίνας"},
{"email":"rada-sirma@example.com","password":"Sirma92^}","name":"Rada Sirma"},
{"email":"uulkan-93@example.com","password":"Kumushbekov93^#","name":"Uulkan Kumushbekov"},
{"email":"cihan_89@example.com","password":"Karalar89+(","name":"Cihan Karalar"},
{"email":"Ερμείας92@example.com","password":"Κοντόσταυλος92^","name":"Ερμείας Κοντόσταυλος"},
{"email":"esteban95@example.com","password":"Mendoza95)^","name":"Esteban Mendoza"},
{"email":"ivana-96@example.com","password":"Štefanko96*(","name":"Ivana Štefanko"},
{"email":"léoperrin@example.com","password":"Perrin90^(","name":"Léo Perrin"},
{"email":"nelu-russo@example.com","password":"Russo87\u0026(","name":"Nelu Russo"},
{"email":"Élouan86@example.com","password":"Reynaud86$*","name":"Élouan Reynaud"},
{"email":"subash_chand@example.com","password":"Chand86*$","name":"Subash Chand"},
{"email":"iacob-burtea@example.com","password":"Burtea87%)","name":"Iacob Burtea"},
{"email":"Ηρόδοτος_95@example.com","password":"Βιτάλης95($","name":"Ηρόδοτος Βιτάλης"},
{"email":"demeter-85@example.com","password":"Chudík85{","name":"Demeter Chudík"},
{"email":"neven-89@example.com","password":"Bašić89)#","name":"Neven Bašić"},
{"email":"rodrigo_89@example.com","password":"León89@+","name":"Rodrigo León"},
{"email":"cristian-92@example.com","password":"Morar92{%","name":"Cristian Morar"},
{"email":"Ιάσονας_95@example.com","password":"Οικονόμου95$","name":"Ιάσονας Οικονόμου"},
{"email":"diego_91@example.com","password":"Cordier91!_","name":"Diego Cordier"},
{"email":"韩_元@example.com","password":"元91)!","name":"韩 元"},
{"email":"jela-dusík@example.com","password":"Dusík93\u0026=","name":"Jela Dusík"},
{"email":"Αφαρέας_85@example.com","password":"Ουζουνίδης85)=","name":"Αφαρέας Ουζουνίδης"},
{"email":"liviu-84@example.com","password":"Turcdeanu84@","name":"Liviu Turcdeanu"},
{"email":"angel-tripp@example.com","password":"Tripp86#%","name":"Angel Tripp"},
{"email":"amza97@example.com","password":"Ivănceanu97(#","name":"Amza Ivănceanu"},
{"email":"alba-gómez@example.com","password":"Gómez91}","name":"Alba Gómez"},
{"email":"jerry_96@example.com","password":"Alvarez96\u0026^","name":"Jerry Alvarez"},
{"email":"امیرمحمد-97@example.com","password":"صیادی97*","name":"امیرمحمد صیادی"},
{"email":"rupak-98@example.com","password":"Shrestha98*{","name":"Rupak Shrestha"},
{"email":"molly-84@example.com","password":"Crosbie84~\u0026","name":"Molly Crosbie"},
{"email":"andrés.may@example.com","password":"May90@@","name":"Andrés May"},
{"email":"Μένανδρος94@example.com","password":"Δοξαράς94{(","name":"Μένανδρος Δοξαράς"},
{"email":"guillaume-84@example.com","password":"Remy84(_","name":"Guillaume Remy"},
{"email":"sabahattin-98@example.com","password":"Koçhisar98)~","name":"Sabahattin Koçhisar"},
{"email":"mirela-94@example.com","password":"Văleanu94+@","name":"Mirela Văleanu"},
{"email":"kanti-89@example.com","password":"Budathoki89~+","name":"Kanti Budathoki"},
{"email":"Ερμογένης91@example.com","password":"Γεννάδιος91@~","name":"Ερμογένης Γεννάδιος"},
{"email":"léa_nicolas@example.com","password":"Nicolas87){","name":"Léa Nicolas"},
{"email":"felix.rus@example.com","password":"Rus86\u0026~","name":"Felix Rus"},
{"email":"salvador_87@example.com","password":"Reyes87!","name":"Salvador Reyes"},
{"email":"jamie.pawson@example.com","password":"Pawson89$!","name":"Jamie Pawson"},
{"email":"Çağerdem@example.com","password":"Erdem87{_","name":"Çağ Erdem"},
{"email":"沈婷@example.com","password":"婷96@+","name":"沈 婷"},
{"email":"alara yavuz@example.com","password":"89)%","name":"Alara Yavuz "},
{"email":"eugenbogza@example.com","password":"Bogza84()","name":"Eugen Bogza"},
{"email":"stana96@example.com","password":"Astaloș96==","name":"Stana Astaloș"},
{"email":"paula-92@example.com","password":"Cordero92~*","name":"Paula Cordero"},
{"email":"matthias_94@example.com","password":"Huber94~@","name":"Matthias Huber"},
{"email":"katja96@example.com","password":"Potočnik96+\u0026","name":"Katja Potočnik"},
{"email":"nasyukat_92@example.com","password":"Erkinov92=^","name":"Nasyukat Erkinov"},
{"email":"florentin86@example.com","password":"Goga86{!","name":"Florentin Goga"},
{"email":"caitlyn-88@example.com","password":"Regan88{}","name":"Caitlyn Regan"},
{"email":"omar-ahelluc@example.com","password":"Ahelluc98!@","name":"Omar Ahelluc"},
{"email":"wolfgang-95@example.com","password":"Reiter95$~","name":"Wolfgang Reiter"},
{"email":"axelle-86@example.com","password":"Verlinden86_@","name":"Axelle Verlinden"},
{"email":"enes-85@example.com","password":"Sijerčić85@","name":"Enes Sijerčić"},
{"email":"cédric-96@example.com","password":"Michel96+^","name":"Cédric Michel"},
{"email":"octav-96@example.com","password":"Văluță96!)","name":"Octav Văluță"},
{"email":"voichița91@example.com","password":"Cucu91$+","name":"Voichița Cucu"},
{"email":"augustín88@example.com","password":"Chalupka88@#","name":"Augustín Chalupka"},
{"email":"aurel98@example.com","password":"Moroșanu98@","name":"Aurel Moroșanu"},
{"email":"Βελλεροφόντης93@example.com","password":"Κοντόσταυλος93_#","name":"Βελλεροφόντης Κοντόσταυλος"},
{"email":"rupak_kirati@example.com","password":"Kirati98{\u0026","name":"Rupak Kirati"},
{"email":"lucia96@example.com","password":"Martino96@)","name":"Lucia Martino"},
{"email":"finnharwood@example.com","password":"Harwood93$#","name":"Finn Harwood"},
{"email":"Λύκος84@example.com","password":"Βιτάλη84@=","name":"Λύκος Βιτάλη"},
{"email":"bhumika_95@example.com","password":"Kirati95*(","name":"Bhumika Kirati"},
{"email":"mason.ward@example.com","password":"Ward94!^","name":"Mason Ward"},
{"email":"ebba_isakson@example.com","password":"Isakson86)","name":"Ebba Isakson"},
{"email":"laili-86@example.com","password":"Erkinov86}~","name":"Laili Erkinov"},
{"email":"dorli87@example.com","password":"Hrușcă87~#","name":"Dorli Hrușcă"},
{"email":"julian_85@example.com","password":"Berger85(","name":"Julian Berger"},
{"email":"Аида_96@example.com","password":"Седых96*%","name":"Аида Седых"},
{"email":"németh-83@example.com","password":"Katalin83*_","name":"Németh Katalin"},
{"email":"mirtel_91@example.com","password":"Kuusik91}^","name":"Mirtel Kuusik"},
{"email":"joe-rose@example.com","password":"Rose96^$","name":"Joe Rose"},
{"email":"mona-94@example.com","password":"Mihăiță94%^","name":"Mona Mihăiță"},
{"email":"renéŠimek@example.com","password":"Šimek88=\u0026","name":"René Šimek"},
{"email":"anastasia_91@example.com","password":"Blănculescu91#","name":"Anastasia Blănculescu"},
{"email":"justin92@example.com","password":"Lambert92{%","name":"Justin Lambert"},
{"email":"csomor-88@example.com","password":"Sámson88=^","name":"Csomor Sámson"},
{"email":"silvian-84@example.com","password":"Grigoriu84%#","name":"Silvian Grigoriu"},
{"email":"jason van de-95@example.com","password":"Velde95)(","name":"Jason Van De Velde"},
{"email":"Σοφία-95@example.com","password":"Λιάπης95$_","name":"Σοφία Λιάπης"},
{"email":"Ευτρόπιος_89@example.com","password":"Αναστασιάδης89$%","name":"Ευτρόπιος Αναστασιάδης"},
{"email":"ileana-95@example.com","password":"Vădineanu95}*","name":"Ileana Vădineanu"},
{"email":"soňa_85@example.com","password":"Kližan85*}","name":"Soňa Kližan"},
{"email":"bekten97@example.com","password":"Isakov97_{","name":"Bekten Isakov"},
{"email":"greta.amato@example.com","password":"Amato87*}","name":"Greta Amato"},
{"email":"narcis-90@example.com","password":"Andrieș90\u0026","name":"Narcis Andrieș"},
{"email":"upol-84@example.com","password":"Alimbekov84$+","name":"Upol Alimbekov"},
{"email":"zenovia-94@example.com","password":"Tomoioagă94)#","name":"Zenovia Tomoioagă"},
{"email":"ethan-86@example.com","password":"Stevens86$)","name":"Ethan Stevens"},
{"email":"iulia-89@example.com","password":"Liiceanu89}_","name":"Iulia Liiceanu"},
{"email":"Ελισσώνας-92@example.com","password":"Γούσιος92\u0026)","name":"Ελισσώνας Γούσιος"},
{"email":"uma_88@example.com","password":"Majstorović88!}","name":"Uma Majstorović"},
{"email":"elvira-88@example.com","password":"Nicoară88__","name":"Elvira Nicoară"},
{"email":"sofía93@example.com","password":"Santiago93*}","name":"Sofía Santiago"},
{"email":"agripina_84@example.com","password":"Bratu84\u0026^","name":"Agripina Bratu"},
{"email":"sarah.reeves@example.com","password":"Reeves84$=","name":"Sarah Reeves"},
{"email":"pamfil_89@example.com","password":"Dobrin89{#","name":"Pamfil Dobrin"},
{"email":"Αφαρέας86@example.com","password":"Χατζηιωάννου86!@","name":"Αφαρέας Χατζηιωάννου"},
{"email":"Ηλιόδωρος90@example.com","password":"Καλαμογδάρτης90)_","name":"Ηλιόδωρος Καλαμογδάρτης"},
{"email":"전-수빈@example.com","password":"수빈98}^","name":"전 수빈"},
{"email":"mildred-87@example.com","password":"Schneider87$%","name":"Mildred Schneider"},
{"email":"teohari-86@example.com","password":"Sandu86#_","name":"Teohari Sandu"},
{"email":"timotej-94@example.com","password":"Melicherčík94@)","name":"Timotej Melicherčík"},
{"email":"fabian-94@example.com","password":"Averescu94#*","name":"Fabian Averescu"},
{"email":"matúš95@example.com","password":"Michálek95=%","name":"Matúš Michálek"},
{"email":"marisol_90@example.com","password":"Palma90}~","name":"Marisol Palma"},
{"email":"alžbeta96@example.com","password":"Dudok96=^","name":"Alžbeta Dudok"},
{"email":"mitică85@example.com","password":"Costea85@","name":"Mitică Costea"},
{"email":"Μίμας-93@example.com","password":"Κούνδουρος93=*","name":"Μίμας Κούνδουρος"},
{"email":"janina97@example.com","password":"Brumaru97#*","name":"Janina Brumaru"},
{"email":"achim87@example.com","password":"Predescu87=*","name":"Achim Predescu"},
{"email":"david_96@example.com","password":"Christiaens96+)","name":"David Christiaens"},
{"email":"florența-97@example.com","password":"Deac97@(","name":"Florența Deac"},
{"email":"rodicalascu@example.com","password":"Lascu84${","name":"Rodica Lascu"},
{"email":"Πτολεμαίος86@example.com","password":"Λαμπρόπουλος86^*","name":"Πτολεμαίος Λαμπρόπουλος"},
{"email":"aurelia-94@example.com","password":"Răceanu94)@","name":"Aurelia Răceanu"},
{"email":"maria_98@example.com","password":"Orleanu98*^","name":"Maria Orleanu"},
{"email":"elena84@example.com","password":"Manțog84_#","name":"Elena Manțog"},
{"email":"nyitrai_98@example.com","password":"Sári98)+","name":"Nyitrai Sári"},
{"email":"lisa-vink@example.com","password":"Vink97)_","name":"Lisa Vink"},
{"email":"morgane96@example.com","password":"Goossens96@~","name":"Morgane Goossens"},
{"email":"izidor98@example.com","password":"Podhradský98++","name":"Izidor Podhradský"},
{"email":"alla_erlanov@example.com","password":"Erlanov90{\u0026","name":"Alla Erlanov"},
{"email":"letiția_92@example.com","password":"Sassu92+#","name":"Letiția Sassu"},
{"email":"هند-85@example.com","password":"الفوزان85+=","name":"هند الفوزان"},
{"email":"nurila-91@example.com","password":"Alimbekov91~+","name":"Nurila Alimbekov"},
{"email":"rené_masný@example.com","password":"Masný96^*","name":"René Masný"},
{"email":"dylan-92@example.com","password":"Chapman92+","name":"Dylan Chapman"},
{"email":"Επιμηθέας95@example.com","password":"Σαμαράς95~}","name":"Επιμηθέας Σαμαράς"},
{"email":"asya_dereli@example.com","password":"Dereli96$_","name":"Asya Dereli"},
{"email":"paula85@example.com","password":"Nicoară85~!","name":"Paula Nicoară"},
{"email":"artur_88@example.com","password":"Vasiliev88^^","name":"Artur Vasiliev"},
{"email":"robert-black@example.com","password":"Black98~","name":"Robert Black"},
{"email":"정.아름@example.com","password":"아름97$","name":"정 아름"},
{"email":"aliskiazim@example.com","password":"Kiazim83%}","name":"Alis Kiazim"},
{"email":"vendelín-94@example.com","password":"Vasko94$@","name":"Vendelín Vasko"},
{"email":"Αφαρέας94@example.com","password":"Ανδρέου94#","name":"Αφαρέας Ανδρέου"},
{"email":"bruno_puška@example.com","password":"Puška85@~","name":"Bruno Puška"},
{"email":"Δαμέας_98@example.com","password":"Αλεβιζόπουλος98(+","name":"Δαμέας Αλεβιζόπουλος"},
{"email":"Влад_97@example.com","password":"Ильин97~=","name":"Влад Ильин"},
{"email":"francisca_88@example.com","password":"Correia88@!","name":"Francisca Correia"},
{"email":"hàlợi@example.com","password":"Lợi87~%","name":"Hà Lợi"},
{"email":"pablo89@example.com","password":"Alvarez89!","name":"Pablo Alvarez"},
{"email":"孔_淑@example.com","password":"淑92}^","name":"孔 淑"},
{"email":"lucas_mason@example.com","password":"Mason96=@","name":"Lucas Mason"},
{"email":"martha_henry@example.com","password":"Henry97__","name":"Martha Henry"},
{"email":"semih-89@example.com","password":"Topsakal89_#","name":"Semih Topsakal"},
{"email":"leopoldina97@example.com","password":"Panțuru97^#","name":"Leopoldina Panțuru"},
{"email":"michael98@example.com","password":"Goodwin98}(","name":"Michael Goodwin"},
{"email":"octaviana84@example.com","password":"Topor84!#","name":"Octaviana Topor"},
{"email":"leontina_86@example.com","password":"Chișu86@(","name":"Leontina Chișu"},
{"email":"Филипп_92@example.com","password":"Черноусов92^","name":"Филипп Черноусов"},
{"email":"evan.wright@example.com","password":"Wright92)$","name":"Evan Wright"},
{"email":"gerrit van der92@example.com","password":"Veen92}+","name":"Gerrit van der Veen"},
{"email":"božidara-87@example.com","password":"Durdík87#_","name":"Božidara Durdík"},
{"email":"angela_90@example.com","password":"Štefanovič90_*","name":"Angela Štefanovič"},
{"email":"Κλέων92@example.com","password":"Φραγκούδης92}%","name":"Κλέων Φραγκούδης"},
{"email":"Αρχέλαος-93@example.com","password":"Μιχαλολιάκος93!%","name":"Αρχέλαος Μιχαλολιάκος"},
{"email":"octavia-92@example.com","password":"Goian92_$","name":"Octavia Goian"},
{"email":"mathilda_93@example.com","password":"Becker93{~","name":"Mathilda Becker"},
{"email":"igor-mečiar@example.com","password":"Mečiar88@\u0026","name":"Igor Mečiar"},
{"email":"radoslav_93@example.com","password":"Janek93_$","name":"Radoslav Janek"},
{"email":"pamela-88@example.com","password":"Neacșu88}}","name":"Pamela Neacșu"},
{"email":"sava.rusca@example.com","password":"Rusca87!%","name":"Sava Rusca"},
{"email":"catinca-98@example.com","password":"Firulescu98*\u0026","name":"Catinca Firulescu"},
{"email":"henry.lodge@example.com","password":"Lodge86(_","name":"Henry Lodge"},
{"email":"lieke-97@example.com","password":"Molenaar97(}","name":"Lieke Molenaar"},
{"email":"孟_霖@example.com","password":"霖85!%","name":"孟 霖"},
{"email":"nurlana-86@example.com","password":"Mahmudzadə86#_","name":"Nurlana Mahmudzadə"},
{"email":"floriana84@example.com","password":"Eșanu84!~","name":"Floriana Eșanu"},
{"email":"simona93@example.com","password":"Râpeanu93_@","name":"Simona Râpeanu"},
{"email":"dumitru98@example.com","password":"Turcdeanu98*(","name":"Dumitru Turcdeanu"},
{"email":"costin-92@example.com","password":"Bonciu92{_","name":"Costin Bonciu"},
{"email":"viviana96@example.com","password":"Ungureanu96+=","name":"Viviana Ungureanu"},
{"email":"eva_Özkan@example.com","password":"Özkan86%}","name":"Eva Özkan"},
{"email":"Αρισταίος_92@example.com","password":"Ασπάσιος92$_","name":"Αρισταίος Ασπάσιος"},
{"email":"radúz-baša@example.com","password":"Baša96$#","name":"Radúz Baša"},
{"email":"Λυσικλής-84@example.com","password":"Παπανικολάου84}{","name":"Λυσικλής Παπανικολάου"},
{"email":"ilinca-97@example.com","password":"Cătunean97%\u0026","name":"Ilinca Cătunean"},
{"email":"jasmin-braun@example.com","password":"Braun92(!","name":"Jasmin Braun"},
{"email":"margaréta-90@example.com","password":"Klokoč90^+","name":"Margaréta Klokoč"},
{"email":"aksana_93@example.com","password":"Salamatov93#}","name":"Aksana Salamatov"},
{"email":"başak-85@example.com","password":"Özgür85+=","name":"Başak Özgür"},
{"email":"avram-96@example.com","password":"Calotescu96%\u0026","name":"Avram Calotescu"},
{"email":"jeana-95@example.com","password":"Tatomirescu95=","name":"Jeana Tatomirescu"},
{"email":"Εύδοξος98@example.com","password":"Διδασκάλου98*%","name":"Εύδοξος Διδασκάλου"},
{"email":"Ηρακλείδης_93@example.com","password":"Παυλόπουλος93({","name":"Ηρακλείδης Παυλόπουλος"},
{"email":"milica-94@example.com","password":"Michalko94}^","name":"Milica Michalko"},
{"email":"Ζώσιμος_93@example.com","password":"Παπάγος93!~","name":"Ζώσιμος Παπάγος"},
{"email":"billy_young@example.com","password":"Young97)*","name":"Billy Young"},
{"email":"philip_94@example.com","password":"Kristensen94*)","name":"Philip Kristensen"},
{"email":"왕혜진@example.com","password":"혜진85+@","name":"왕 혜진"},
{"email":"السيدة84@example.com","password":"الطرابلسي84{+","name":"السيدة الطرابلسي"},
{"email":"sebastian98@example.com","password":"Bogza98~","name":"Sebastian Bogza"},
{"email":"rosa_87@example.com","password":"Cázares87==","name":"Rosa Cázares"},
{"email":"Ľubica92@example.com","password":"Šváby92{~","name":"Ľubica Šváby"},
{"email":"Αρισταγόρας97@example.com","password":"Ζωγράφου97$$","name":"Αρισταγόρας Ζωγράφου"},
{"email":"anișoara_92@example.com","password":"Dobroiu92#*","name":"Anișoara Dobroiu"},
{"email":"vieroslava_96@example.com","password":"Valenta96}~","name":"Vieroslava Valenta"},
{"email":"mona98@example.com","password":"Romanescu98!#","name":"Mona Romanescu"},
{"email":"ruxanda-92@example.com","password":"Mazilu92~%","name":"Ruxanda Mazilu"},
{"email":"margita-hric@example.com","password":"Hric89_","name":"Margita Hric"},
{"email":"narcisa97@example.com","password":"Dogaru97_+","name":"Narcisa Dogaru"},
{"email":"Ισίδωρος-97@example.com","password":"Ζάρκος97^(","name":"Ισίδωρος Ζάρκος"},
{"email":"Ασπάσιος_96@example.com","password":"Μήτζου96\u0026~","name":"Ασπάσιος Μήτζου"},
{"email":"İsmail95@example.com","password":"Terman95$$","name":"İsmail Terman"},
{"email":"grigore_86@example.com","password":"Predescu86@","name":"Grigore Predescu"},
{"email":"Κίμων-93@example.com","password":"Κασιδιάρης93!","name":"Κίμων Κασιδιάρης"},
{"email":"白娴@example.com","password":"娴92_}","name":"白 娴"},
{"email":"annie_simard@example.com","password":"Simard95}%","name":"Annie Simard"},
{"email":"brian94@example.com","password":"Carroll94*","name":"Brian Carroll"},
{"email":"vũ.lợi@example.com","password":"Lợi98\u0026#","name":"Vũ Lợi"},
{"email":"sudha-86@example.com","password":"Manandhar86$","name":"Sudha Manandhar"},
{"email":"Ιάκωβος89@example.com","password":"Σπηλιωτόπουλος89~*","name":"Ιάκωβος Σπηλιωτόπουλος"},
{"email":"Ștefana_89@example.com","password":"Sandu89(=","name":"Ștefana Sandu"},
{"email":"eleonóra-92@example.com","password":"Fajnor92*^","name":"Eleonóra Fajnor"}
]
